{
	"results": [{
		"__metadata": {
			"id": "https://fsc2-a73e63587.dispatcher.hana.ondemand.com/sap/opu/odata/sap/ZS_AGS_FSC2_SRV/NotesSet('0010252522')",
			"uri": "https://fsc2-a73e63587.dispatcher.hana.ondemand.com/sap/opu/odata/sap/ZS_AGS_FSC2_SRV/NotesSet('0010252522')",
			"type": "ZS_AGS_FSC2_SRV.Notes"
		},
		"id": "0010252522",
		"process_type": "ZS90",
		"notes_type": "",
		"notes": "",
		"tdformat": "*",
		"tdline": "Inbound Email Summary"
	}, {
		"__metadata": {
			"id": "https://fsc2-a73e63587.dispatcher.hana.ondemand.com/sap/opu/odata/sap/ZS_AGS_FSC2_SRV/NotesSet('0010252522')",
			"uri": "https://fsc2-a73e63587.dispatcher.hana.ondemand.com/sap/opu/odata/sap/ZS_AGS_FSC2_SRV/NotesSet('0010252522')",
			"type": "ZS_AGS_FSC2_SRV.Notes"
		},
		"id": "0010252522",
		"process_type": "ZS90",
		"notes_type": "",
		"notes": "",
		"tdformat": "*",
		"tdline": "Inbound Email Summary"
	}, {
		"__metadata": {
			"id": "https://fsc2-a73e63587.dispatcher.hana.ondemand.com/sap/opu/odata/sap/ZS_AGS_FSC2_SRV/NotesSet('0010252522')",
			"uri": "https://fsc2-a73e63587.dispatcher.hana.ondemand.com/sap/opu/odata/sap/ZS_AGS_FSC2_SRV/NotesSet('0010252522')",
			"type": "ZS_AGS_FSC2_SRV.Notes"
		},
		"id": "0010252522",
		"process_type": "ZS90",
		"notes_type": "",
		"notes": "",
		"tdformat": "*",
		"tdline": "Long Zheng"
	}, {
		"__metadata": {
			"id": "https://fsc2-a73e63587.dispatcher.hana.ondemand.com/sap/opu/odata/sap/ZS_AGS_FSC2_SRV/NotesSet('0010252522')",
			"uri": "https://fsc2-a73e63587.dispatcher.hana.ondemand.com/sap/opu/odata/sap/ZS_AGS_FSC2_SRV/NotesSet('0010252522')",
			"type": "ZS_AGS_FSC2_SRV.Notes"
		},
		"id": "0010252522",
		"process_type": "ZS90",
		"notes_type": "",
		"notes": "",
		"tdformat": "*",
		"tdline": "Outbound Email Summary"
	}, {
		"__metadata": {
			"id": "https://fsc2-a73e63587.dispatcher.hana.ondemand.com/sap/opu/odata/sap/ZS_AGS_FSC2_SRV/NotesSet('0010252522')",
			"uri": "https://fsc2-a73e63587.dispatcher.hana.ondemand.com/sap/opu/odata/sap/ZS_AGS_FSC2_SRV/NotesSet('0010252522')",
			"type": "ZS_AGS_FSC2_SRV.Notes"
		},
		"id": "0010252522",
		"process_type": "ZS90",
		"notes_type": "",
		"notes": "",
		"tdformat": "*",
		"tdline": "together with employee preferences in terms of companies they want to"
	}, {
		"__metadata": {
			"id": "https://fsc2-a73e63587.dispatcher.hana.ondemand.com/sap/opu/odata/sap/ZS_AGS_FSC2_SRV/NotesSet('0010252522')",
			"uri": "https://fsc2-a73e63587.dispatcher.hana.ondemand.com/sap/opu/odata/sap/ZS_AGS_FSC2_SRV/NotesSet('0010252522')",
			"type": "ZS_AGS_FSC2_SRV.Notes"
		},
		"id": "0010252522",
		"process_type": "ZS90",
		"notes_type": "",
		"notes": "",
		"tdformat": "",
		"tdline": "work for prove that growth occurs when a company really focuses on"
	}, {
		"__metadata": {
			"id": "https://fsc2-a73e63587.dispatcher.hana.ondemand.com/sap/opu/odata/sap/ZS_AGS_FSC2_SRV/NotesSet('0010252522')",
			"uri": "https://fsc2-a73e63587.dispatcher.hana.ondemand.com/sap/opu/odata/sap/ZS_AGS_FSC2_SRV/NotesSet('0010252522')",
			"type": "ZS_AGS_FSC2_SRV.Notes"
		},
		"id": "0010252522",
		"process_type": "ZS90",
		"notes_type": "",
		"notes": "",
		"tdformat": "",
		"tdline": "purpose-driven initiatives. There was a study by EY and HBR recently"
	}, {
		"__metadata": {
			"id": "https://fsc2-a73e63587.dispatcher.hana.ondemand.com/sap/opu/odata/sap/ZS_AGS_FSC2_SRV/NotesSet('0010252522')",
			"uri": "https://fsc2-a73e63587.dispatcher.hana.ondemand.com/sap/opu/odata/sap/ZS_AGS_FSC2_SRV/NotesSet('0010252522')",
			"type": "ZS_AGS_FSC2_SRV.Notes"
		},
		"id": "0010252522",
		"process_type": "ZS90",
		"notes_type": "",
		"notes": "",
		"tdformat": "",
		"tdline": "that talked about how 83 percent of companies that over-perform on"
	}, {
		"__metadata": {
			"id": "https://fsc2-a73e63587.dispatcher.hana.ondemand.com/sap/opu/odata/sap/ZS_AGS_FSC2_SRV/NotesSet('0010252522')",
			"uri": "https://fsc2-a73e63587.dispatcher.hana.ondemand.com/sap/opu/odata/sap/ZS_AGS_FSC2_SRV/NotesSet('0010252522')",
			"type": "ZS_AGS_FSC2_SRV.Notes"
		},
		"id": "0010252522",
		"process_type": "ZS90",
		"notes_type": "",
		"notes": "",
		"tdformat": "",
		"tdline": "revenue growth link everything they do to brand purpose, as opposed to"
	}, {
		"__metadata": {
			"id": "https://fsc2-a73e63587.dispatcher.hana.ondemand.com/sap/opu/odata/sap/ZS_AGS_FSC2_SRV/NotesSet('0010252522')",
			"uri": "https://fsc2-a73e63587.dispatcher.hana.ondemand.com/sap/opu/odata/sap/ZS_AGS_FSC2_SRV/NotesSet('0010252522')",
			"type": "ZS_AGS_FSC2_SRV.Notes"
		},
		"id": "0010252522",
		"process_type": "ZS90",
		"notes_type": "",
		"notes": "",
		"tdformat": "",
		"tdline": "only 31 percent of under-performers. What that tells us is that"
	}, {
		"__metadata": {
			"id": "https://fsc2-a73e63587.dispatcher.hana.ondemand.com/sap/opu/odata/sap/ZS_AGS_FSC2_SRV/NotesSet('0010252522')",
			"uri": "https://fsc2-a73e63587.dispatcher.hana.ondemand.com/sap/opu/odata/sap/ZS_AGS_FSC2_SRV/NotesSet('0010252522')",
			"type": "ZS_AGS_FSC2_SRV.Notes"
		},
		"id": "0010252522",
		"process_type": "ZS90",
		"notes_type": "",
		"notes": "",
		"tdformat": "",
		"tdline": "companies who deliver and innovate against a strong set of values and"
	}, {
		"__metadata": {
			"id": "https://fsc2-a73e63587.dispatcher.hana.ondemand.com/sap/opu/odata/sap/ZS_AGS_FSC2_SRV/NotesSet('0010252522')",
			"uri": "https://fsc2-a73e63587.dispatcher.hana.ondemand.com/sap/opu/odata/sap/ZS_AGS_FSC2_SRV/NotesSet('0010252522')",
			"type": "ZS_AGS_FSC2_SRV.Notes"
		},
		"id": "0010252522",
		"process_type": "ZS90",
		"notes_type": "",
		"notes": "",
		"tdformat": "",
		"tdline": "use their platform to work towards a higher good are more profitable"
	}, {
		"__metadata": {
			"id": "https://fsc2-a73e63587.dispatcher.hana.ondemand.com/sap/opu/odata/sap/ZS_AGS_FSC2_SRV/NotesSet('0010252522')",
			"uri": "https://fsc2-a73e63587.dispatcher.hana.ondemand.com/sap/opu/odata/sap/ZS_AGS_FSC2_SRV/NotesSet('0010252522')",
			"type": "ZS_AGS_FSC2_SRV.Notes"
		},
		"id": "0010252522",
		"process_type": "ZS90",
		"notes_type": "",
		"notes": "",
		"tdformat": "",
		"tdline": "than companies who are not."
	}, {
		"__metadata": {
			"id": "https://fsc2-a73e63587.dispatcher.hana.ondemand.com/sap/opu/odata/sap/ZS_AGS_FSC2_SRV/NotesSet('0010252522')",
			"uri": "https://fsc2-a73e63587.dispatcher.hana.ondemand.com/sap/opu/odata/sap/ZS_AGS_FSC2_SRV/NotesSet('0010252522')",
			"type": "ZS_AGS_FSC2_SRV.Notes"
		},
		"id": "0010252522",
		"process_type": "ZS90",
		"notes_type": "",
		"notes": "",
		"tdformat": "*",
		"tdline": "Comments for expected action"
	}, {
		"__metadata": {
			"id": "https://fsc2-a73e63587.dispatcher.hana.ondemand.com/sap/opu/odata/sap/ZS_AGS_FSC2_SRV/NotesSet('0010252522')",
			"uri": "https://fsc2-a73e63587.dispatcher.hana.ondemand.com/sap/opu/odata/sap/ZS_AGS_FSC2_SRV/NotesSet('0010252522')",
			"type": "ZS_AGS_FSC2_SRV.Notes"
		},
		"id": "0010252522",
		"process_type": "ZS90",
		"notes_type": "",
		"notes": "",
		"tdformat": "*",
		"tdline": "When consumers have a choice between companies who are invested in"
	}, {
		"__metadata": {
			"id": "https://fsc2-a73e63587.dispatcher.hana.ondemand.com/sap/opu/odata/sap/ZS_AGS_FSC2_SRV/NotesSet('0010252522')",
			"uri": "https://fsc2-a73e63587.dispatcher.hana.ondemand.com/sap/opu/odata/sap/ZS_AGS_FSC2_SRV/NotesSet('0010252522')",
			"type": "ZS_AGS_FSC2_SRV.Notes"
		},
		"id": "0010252522",
		"process_type": "ZS90",
		"notes_type": "",
		"notes": "",
		"tdformat": "",
		"tdline": "giving back versus a company that doesn’t, today’s consumers are"
	}, {
		"__metadata": {
			"id": "https://fsc2-a73e63587.dispatcher.hana.ondemand.com/sap/opu/odata/sap/ZS_AGS_FSC2_SRV/NotesSet('0010252522')",
			"uri": "https://fsc2-a73e63587.dispatcher.hana.ondemand.com/sap/opu/odata/sap/ZS_AGS_FSC2_SRV/NotesSet('0010252522')",
			"type": "ZS_AGS_FSC2_SRV.Notes"
		},
		"id": "0010252522",
		"process_type": "ZS90",
		"notes_type": "",
		"notes": "",
		"tdformat": "",
		"tdline": "absolutely going to go towards the company that is using their platform"
	}, {
		"__metadata": {
			"id": "https://fsc2-a73e63587.dispatcher.hana.ondemand.com/sap/opu/odata/sap/ZS_AGS_FSC2_SRV/NotesSet('0010252522')",
			"uri": "https://fsc2-a73e63587.dispatcher.hana.ondemand.com/sap/opu/odata/sap/ZS_AGS_FSC2_SRV/NotesSet('0010252522')",
			"type": "ZS_AGS_FSC2_SRV.Notes"
		},
		"id": "0010252522",
		"process_type": "ZS90",
		"notes_type": "",
		"notes": "",
		"tdformat": "",
		"tdline": "for good. This is both a result of our younger generations that are"
	}, {
		"__metadata": {
			"id": "https://fsc2-a73e63587.dispatcher.hana.ondemand.com/sap/opu/odata/sap/ZS_AGS_FSC2_SRV/NotesSet('0010252522')",
			"uri": "https://fsc2-a73e63587.dispatcher.hana.ondemand.com/sap/opu/odata/sap/ZS_AGS_FSC2_SRV/NotesSet('0010252522')",
			"type": "ZS_AGS_FSC2_SRV.Notes"
		},
		"id": "0010252522",
		"process_type": "ZS90",
		"notes_type": "",
		"notes": "",
		"tdformat": "",
		"tdline": "coming into the workforce, but also because of more mature demographics"
	}, {
		"__metadata": {
			"id": "https://fsc2-a73e63587.dispatcher.hana.ondemand.com/sap/opu/odata/sap/ZS_AGS_FSC2_SRV/NotesSet('0010252522')",
			"uri": "https://fsc2-a73e63587.dispatcher.hana.ondemand.com/sap/opu/odata/sap/ZS_AGS_FSC2_SRV/NotesSet('0010252522')",
			"type": "ZS_AGS_FSC2_SRV.Notes"
		},
		"id": "0010252522",
		"process_type": "ZS90",
		"notes_type": "",
		"notes": "",
		"tdformat": "",
		"tdline": "who care just as much as younger millennials."
	}, {
		"__metadata": {
			"id": "https://fsc2-a73e63587.dispatcher.hana.ondemand.com/sap/opu/odata/sap/ZS_AGS_FSC2_SRV/NotesSet('0010252522')",
			"uri": "https://fsc2-a73e63587.dispatcher.hana.ondemand.com/sap/opu/odata/sap/ZS_AGS_FSC2_SRV/NotesSet('0010252522')",
			"type": "ZS_AGS_FSC2_SRV.Notes"
		},
		"id": "0010252522",
		"process_type": "ZS90",
		"notes_type": "",
		"notes": "",
		"tdformat": "*",
		"tdline": ""
	}, {
		"__metadata": {
			"id": "https://fsc2-a73e63587.dispatcher.hana.ondemand.com/sap/opu/odata/sap/ZS_AGS_FSC2_SRV/NotesSet('0010252522')",
			"uri": "https://fsc2-a73e63587.dispatcher.hana.ondemand.com/sap/opu/odata/sap/ZS_AGS_FSC2_SRV/NotesSet('0010252522')",
			"type": "ZS_AGS_FSC2_SRV.Notes"
		},
		"id": "0010252522",
		"process_type": "ZS90",
		"notes_type": "",
		"notes": "",
		"tdformat": "*",
		"tdline": "That said, when I took on this role, it wasn’t because this research"
	}, {
		"__metadata": {
			"id": "https://fsc2-a73e63587.dispatcher.hana.ondemand.com/sap/opu/odata/sap/ZS_AGS_FSC2_SRV/NotesSet('0010252522')",
			"uri": "https://fsc2-a73e63587.dispatcher.hana.ondemand.com/sap/opu/odata/sap/ZS_AGS_FSC2_SRV/NotesSet('0010252522')",
			"type": "ZS_AGS_FSC2_SRV.Notes"
		},
		"id": "0010252522",
		"process_type": "ZS90",
		"notes_type": "",
		"notes": "",
		"tdformat": "",
		"tdline": "suggested we all of a sudden need to become a company that’s focused on"
	}, {
		"__metadata": {
			"id": "https://fsc2-a73e63587.dispatcher.hana.ondemand.com/sap/opu/odata/sap/ZS_AGS_FSC2_SRV/NotesSet('0010252522')",
			"uri": "https://fsc2-a73e63587.dispatcher.hana.ondemand.com/sap/opu/odata/sap/ZS_AGS_FSC2_SRV/NotesSet('0010252522')",
			"type": "ZS_AGS_FSC2_SRV.Notes"
		},
		"id": "0010252522",
		"process_type": "ZS90",
		"notes_type": "",
		"notes": "",
		"tdformat": "",
		"tdline": "driving good. When SAP was created 46 years ago, we were founded with a"
	}, {
		"__metadata": {
			"id": "https://fsc2-a73e63587.dispatcher.hana.ondemand.com/sap/opu/odata/sap/ZS_AGS_FSC2_SRV/NotesSet('0010252522')",
			"uri": "https://fsc2-a73e63587.dispatcher.hana.ondemand.com/sap/opu/odata/sap/ZS_AGS_FSC2_SRV/NotesSet('0010252522')",
			"type": "ZS_AGS_FSC2_SRV.Notes"
		},
		"id": "0010252522",
		"process_type": "ZS90",
		"notes_type": "",
		"notes": "",
		"tdformat": "",
		"tdline": "vision to help the world run better and improve people’s lives and we"
	}, {
		"__metadata": {
			"id": "https://fsc2-a73e63587.dispatcher.hana.ondemand.com/sap/opu/odata/sap/ZS_AGS_FSC2_SRV/NotesSet('0010252522')",
			"uri": "https://fsc2-a73e63587.dispatcher.hana.ondemand.com/sap/opu/odata/sap/ZS_AGS_FSC2_SRV/NotesSet('0010252522')",
			"type": "ZS_AGS_FSC2_SRV.Notes"
		},
		"id": "0010252522",
		"process_type": "ZS90",
		"notes_type": "",
		"notes": "",
		"tdformat": "",
		"tdline": "were going to do that through technology. Now it’s about helping"
	}, {
		"__metadata": {
			"id": "https://fsc2-a73e63587.dispatcher.hana.ondemand.com/sap/opu/odata/sap/ZS_AGS_FSC2_SRV/NotesSet('0010252522')",
			"uri": "https://fsc2-a73e63587.dispatcher.hana.ondemand.com/sap/opu/odata/sap/ZS_AGS_FSC2_SRV/NotesSet('0010252522')",
			"type": "ZS_AGS_FSC2_SRV.Notes"
		},
		"id": "0010252522",
		"process_type": "ZS90",
		"notes_type": "",
		"notes": "",
		"tdformat": "",
		"tdline": "companies run their businesses as effectively as they possibly can, but"
	}, {
		"__metadata": {
			"id": "https://fsc2-a73e63587.dispatcher.hana.ondemand.com/sap/opu/odata/sap/ZS_AGS_FSC2_SRV/NotesSet('0010252522')",
			"uri": "https://fsc2-a73e63587.dispatcher.hana.ondemand.com/sap/opu/odata/sap/ZS_AGS_FSC2_SRV/NotesSet('0010252522')",
			"type": "ZS_AGS_FSC2_SRV.Notes"
		},
		"id": "0010252522",
		"process_type": "ZS90",
		"notes_type": "",
		"notes": "",
		"tdformat": "",
		"tdline": "also using that same technology to help power agendas of purpose. How do"
	}, {
		"__metadata": {
			"id": "https://fsc2-a73e63587.dispatcher.hana.ondemand.com/sap/opu/odata/sap/ZS_AGS_FSC2_SRV/NotesSet('0010252522')",
			"uri": "https://fsc2-a73e63587.dispatcher.hana.ondemand.com/sap/opu/odata/sap/ZS_AGS_FSC2_SRV/NotesSet('0010252522')",
			"type": "ZS_AGS_FSC2_SRV.Notes"
		},
		"id": "0010252522",
		"process_type": "ZS90",
		"notes_type": "",
		"notes": "",
		"tdformat": "",
		"tdline": "you really use the technology of a company like SAP and allow a"
	}, {
		"__metadata": {
			"id": "https://fsc2-a73e63587.dispatcher.hana.ondemand.com/sap/opu/odata/sap/ZS_AGS_FSC2_SRV/NotesSet('0010252522')",
			"uri": "https://fsc2-a73e63587.dispatcher.hana.ondemand.com/sap/opu/odata/sap/ZS_AGS_FSC2_SRV/NotesSet('0010252522')",
			"type": "ZS_AGS_FSC2_SRV.Notes"
		},
		"id": "0010252522",
		"process_type": "ZS90",
		"notes_type": "",
		"notes": "",
		"tdformat": "",
		"tdline": "company’s customers to see the value in terms of how they drive towards"
	}, {
		"__metadata": {
			"id": "https://fsc2-a73e63587.dispatcher.hana.ondemand.com/sap/opu/odata/sap/ZS_AGS_FSC2_SRV/NotesSet('0010252522')",
			"uri": "https://fsc2-a73e63587.dispatcher.hana.ondemand.com/sap/opu/odata/sap/ZS_AGS_FSC2_SRV/NotesSet('0010252522')",
			"type": "ZS_AGS_FSC2_SRV.Notes"
		},
		"id": "0010252522",
		"process_type": "ZS90",
		"notes_type": "",
		"notes": "",
		"tdformat": "",
		"tdline": "their purpose agendas?"
	}, {
		"__metadata": {
			"id": "https://fsc2-a73e63587.dispatcher.hana.ondemand.com/sap/opu/odata/sap/ZS_AGS_FSC2_SRV/NotesSet('0010252522')",
			"uri": "https://fsc2-a73e63587.dispatcher.hana.ondemand.com/sap/opu/odata/sap/ZS_AGS_FSC2_SRV/NotesSet('0010252522')",
			"type": "ZS_AGS_FSC2_SRV.Notes"
		},
		"id": "0010252522",
		"process_type": "ZS90",
		"notes_type": "",
		"notes": "",
		"tdformat": "*",
		"tdline": "YOU MAY ALSO LIKE"
	}, {
		"__metadata": {
			"id": "https://fsc2-a73e63587.dispatcher.hana.ondemand.com/sap/opu/odata/sap/ZS_AGS_FSC2_SRV/NotesSet('0010252522')",
			"uri": "https://fsc2-a73e63587.dispatcher.hana.ondemand.com/sap/opu/odata/sap/ZS_AGS_FSC2_SRV/NotesSet('0010252522')",
			"type": "ZS_AGS_FSC2_SRV.Notes"
		},
		"id": "0010252522",
		"process_type": "ZS90",
		"notes_type": "",
		"notes": "",
		"tdformat": "*",
		"tdline": "Forbes Insights"
	}, {
		"__metadata": {
			"id": "https://fsc2-a73e63587.dispatcher.hana.ondemand.com/sap/opu/odata/sap/ZS_AGS_FSC2_SRV/NotesSet('0010252522')",
			"uri": "https://fsc2-a73e63587.dispatcher.hana.ondemand.com/sap/opu/odata/sap/ZS_AGS_FSC2_SRV/NotesSet('0010252522')",
			"type": "ZS_AGS_FSC2_SRV.Notes"
		},
		"id": "0010252522",
		"process_type": "ZS90",
		"notes_type": "",
		"notes": "",
		"tdformat": "*",
		"tdline": "New Voice Of The Enterprise"
	}, {
		"__metadata": {
			"id": "https://fsc2-a73e63587.dispatcher.hana.ondemand.com/sap/opu/odata/sap/ZS_AGS_FSC2_SRV/NotesSet('0010252522')",
			"uri": "https://fsc2-a73e63587.dispatcher.hana.ondemand.com/sap/opu/odata/sap/ZS_AGS_FSC2_SRV/NotesSet('0010252522')",
			"type": "ZS_AGS_FSC2_SRV.Notes"
		},
		"id": "0010252522",
		"process_type": "ZS90",
		"notes_type": "",
		"notes": "",
		"tdformat": "*",
		"tdline": "Intel AI BrandVoice"
	}, {
		"__metadata": {
			"id": "https://fsc2-a73e63587.dispatcher.hana.ondemand.com/sap/opu/odata/sap/ZS_AGS_FSC2_SRV/NotesSet('0010252522')",
			"uri": "https://fsc2-a73e63587.dispatcher.hana.ondemand.com/sap/opu/odata/sap/ZS_AGS_FSC2_SRV/NotesSet('0010252522')",
			"type": "ZS_AGS_FSC2_SRV.Notes"
		},
		"id": "0010252522",
		"process_type": "ZS90",
		"notes_type": "",
		"notes": "",
		"tdformat": "*",
		"tdline": "How AI Will Change Industrial Labor—And How We Think About Work"
	}, {
		"__metadata": {
			"id": "https://fsc2-a73e63587.dispatcher.hana.ondemand.com/sap/opu/odata/sap/ZS_AGS_FSC2_SRV/NotesSet('0010252522')",
			"uri": "https://fsc2-a73e63587.dispatcher.hana.ondemand.com/sap/opu/odata/sap/ZS_AGS_FSC2_SRV/NotesSet('0010252522')",
			"type": "ZS_AGS_FSC2_SRV.Notes"
		},
		"id": "0010252522",
		"process_type": "ZS90",
		"notes_type": "",
		"notes": "",
		"tdformat": "*",
		"tdline": "Deloitte BrandVoice"
	}, {
		"__metadata": {
			"id": "https://fsc2-a73e63587.dispatcher.hana.ondemand.com/sap/opu/odata/sap/ZS_AGS_FSC2_SRV/NotesSet('0010252522')",
			"uri": "https://fsc2-a73e63587.dispatcher.hana.ondemand.com/sap/opu/odata/sap/ZS_AGS_FSC2_SRV/NotesSet('0010252522')",
			"type": "ZS_AGS_FSC2_SRV.Notes"
		},
		"id": "0010252522",
		"process_type": "ZS90",
		"notes_type": "",
		"notes": "",
		"tdformat": "*",
		"tdline": "The March Toward Equality And Inclusion Must Become A Sprint"
	}, {
		"__metadata": {
			"id": "https://fsc2-a73e63587.dispatcher.hana.ondemand.com/sap/opu/odata/sap/ZS_AGS_FSC2_SRV/NotesSet('0010252522')",
			"uri": "https://fsc2-a73e63587.dispatcher.hana.ondemand.com/sap/opu/odata/sap/ZS_AGS_FSC2_SRV/NotesSet('0010252522')",
			"type": "ZS_AGS_FSC2_SRV.Notes"
		},
		"id": "0010252522",
		"process_type": "ZS90",
		"notes_type": "",
		"notes": "",
		"tdformat": "*",
		"tdline": ""
	}, {
		"__metadata": {
			"id": "https://fsc2-a73e63587.dispatcher.hana.ondemand.com/sap/opu/odata/sap/ZS_AGS_FSC2_SRV/NotesSet('0010252522')",
			"uri": "https://fsc2-a73e63587.dispatcher.hana.ondemand.com/sap/opu/odata/sap/ZS_AGS_FSC2_SRV/NotesSet('0010252522')",
			"type": "ZS_AGS_FSC2_SRV.Notes"
		},
		"id": "0010252522",
		"process_type": "ZS90",
		"notes_type": "",
		"notes": "",
		"tdformat": "*",
		"tdline": "SIMON: You’ve got something unique at SAP and that’s your incredible"
	}, {
		"__metadata": {
			"id": "https://fsc2-a73e63587.dispatcher.hana.ondemand.com/sap/opu/odata/sap/ZS_AGS_FSC2_SRV/NotesSet('0010252522')",
			"uri": "https://fsc2-a73e63587.dispatcher.hana.ondemand.com/sap/opu/odata/sap/ZS_AGS_FSC2_SRV/NotesSet('0010252522')",
			"type": "ZS_AGS_FSC2_SRV.Notes"
		},
		"id": "0010252522",
		"process_type": "ZS90",
		"notes_type": "",
		"notes": "",
		"tdformat": "",
		"tdline": "global customer network. How is SAP’s customer network helping you"
	}, {
		"__metadata": {
			"id": "https://fsc2-a73e63587.dispatcher.hana.ondemand.com/sap/opu/odata/sap/ZS_AGS_FSC2_SRV/NotesSet('0010252522')",
			"uri": "https://fsc2-a73e63587.dispatcher.hana.ondemand.com/sap/opu/odata/sap/ZS_AGS_FSC2_SRV/NotesSet('0010252522')",
			"type": "ZS_AGS_FSC2_SRV.Notes"
		},
		"id": "0010252522",
		"process_type": "ZS90",
		"notes_type": "",
		"notes": "",
		"tdformat": "",
		"tdline": "achieve impact at scale?"
	}, {
		"__metadata": {
			"id": "https://fsc2-a73e63587.dispatcher.hana.ondemand.com/sap/opu/odata/sap/ZS_AGS_FSC2_SRV/NotesSet('0010252522')",
			"uri": "https://fsc2-a73e63587.dispatcher.hana.ondemand.com/sap/opu/odata/sap/ZS_AGS_FSC2_SRV/NotesSet('0010252522')",
			"type": "ZS_AGS_FSC2_SRV.Notes"
		},
		"id": "0010252522",
		"process_type": "ZS90",
		"notes_type": "",
		"notes": "",
		"tdformat": "*",
		"tdline": ""
	}, {
		"__metadata": {
			"id": "https://fsc2-a73e63587.dispatcher.hana.ondemand.com/sap/opu/odata/sap/ZS_AGS_FSC2_SRV/NotesSet('0010252522')",
			"uri": "https://fsc2-a73e63587.dispatcher.hana.ondemand.com/sap/opu/odata/sap/ZS_AGS_FSC2_SRV/NotesSet('0010252522')",
			"type": "ZS_AGS_FSC2_SRV.Notes"
		},
		"id": "0010252522",
		"process_type": "ZS90",
		"notes_type": "",
		"notes": "",
		"tdformat": "*",
		"tdline": "ALICIA: At SAP, we run the largest buying and selling network on the"
	}, {
		"__metadata": {
			"id": "https://fsc2-a73e63587.dispatcher.hana.ondemand.com/sap/opu/odata/sap/ZS_AGS_FSC2_SRV/NotesSet('0010252522')",
			"uri": "https://fsc2-a73e63587.dispatcher.hana.ondemand.com/sap/opu/odata/sap/ZS_AGS_FSC2_SRV/NotesSet('0010252522')",
			"type": "ZS_AGS_FSC2_SRV.Notes"
		},
		"id": "0010252522",
		"process_type": "ZS90",
		"notes_type": "",
		"notes": "",
		"tdformat": "",
		"tdline": "planet called our SAP Ariba Network, which is comprised of two million"
	}, {
		"__metadata": {
			"id": "https://fsc2-a73e63587.dispatcher.hana.ondemand.com/sap/opu/odata/sap/ZS_AGS_FSC2_SRV/NotesSet('0010252522')",
			"uri": "https://fsc2-a73e63587.dispatcher.hana.ondemand.com/sap/opu/odata/sap/ZS_AGS_FSC2_SRV/NotesSet('0010252522')",
			"type": "ZS_AGS_FSC2_SRV.Notes"
		},
		"id": "0010252522",
		"process_type": "ZS90",
		"notes_type": "",
		"notes": "",
		"tdformat": "",
		"tdline": "companies’ buyers and suppliers that are sharing goods and services"
	}, {
		"__metadata": {
			"id": "https://fsc2-a73e63587.dispatcher.hana.ondemand.com/sap/opu/odata/sap/ZS_AGS_FSC2_SRV/NotesSet('0010252522')",
			"uri": "https://fsc2-a73e63587.dispatcher.hana.ondemand.com/sap/opu/odata/sap/ZS_AGS_FSC2_SRV/NotesSet('0010252522')",
			"type": "ZS_AGS_FSC2_SRV.Notes"
		},
		"id": "0010252522",
		"process_type": "ZS90",
		"notes_type": "",
		"notes": "",
		"tdformat": "",
		"tdline": "between one another. One of the things both are challenged with is the"
	}, {
		"__metadata": {
			"id": "https://fsc2-a73e63587.dispatcher.hana.ondemand.com/sap/opu/odata/sap/ZS_AGS_FSC2_SRV/NotesSet('0010252522')",
			"uri": "https://fsc2-a73e63587.dispatcher.hana.ondemand.com/sap/opu/odata/sap/ZS_AGS_FSC2_SRV/NotesSet('0010252522')",
			"type": "ZS_AGS_FSC2_SRV.Notes"
		},
		"id": "0010252522",
		"process_type": "ZS90",
		"notes_type": "",
		"notes": "",
		"tdformat": "",
		"tdline": "responsibility to have a very clean supply chain. Sadly, in today’s"
	}, {
		"__metadata": {
			"id": "https://fsc2-a73e63587.dispatcher.hana.ondemand.com/sap/opu/odata/sap/ZS_AGS_FSC2_SRV/NotesSet('0010252522')",
			"uri": "https://fsc2-a73e63587.dispatcher.hana.ondemand.com/sap/opu/odata/sap/ZS_AGS_FSC2_SRV/NotesSet('0010252522')",
			"type": "ZS_AGS_FSC2_SRV.Notes"
		},
		"id": "0010252522",
		"process_type": "ZS90",
		"notes_type": "",
		"notes": "",
		"tdformat": "",
		"tdline": "environment, we still see modern slavery in the form of a tremendous"
	}, {
		"__metadata": {
			"id": "https://fsc2-a73e63587.dispatcher.hana.ondemand.com/sap/opu/odata/sap/ZS_AGS_FSC2_SRV/NotesSet('0010252522')",
			"uri": "https://fsc2-a73e63587.dispatcher.hana.ondemand.com/sap/opu/odata/sap/ZS_AGS_FSC2_SRV/NotesSet('0010252522')",
			"type": "ZS_AGS_FSC2_SRV.Notes"
		},
		"id": "0010252522",
		"process_type": "ZS90",
		"notes_type": "",
		"notes": "",
		"tdformat": "",
		"tdline": "amount of forced labor in supply chains. With SAP Ariba running the"
	}, {
		"__metadata": {
			"id": "https://fsc2-a73e63587.dispatcher.hana.ondemand.com/sap/opu/odata/sap/ZS_AGS_FSC2_SRV/NotesSet('0010252522')",
			"uri": "https://fsc2-a73e63587.dispatcher.hana.ondemand.com/sap/opu/odata/sap/ZS_AGS_FSC2_SRV/NotesSet('0010252522')",
			"type": "ZS_AGS_FSC2_SRV.Notes"
		},
		"id": "0010252522",
		"process_type": "ZS90",
		"notes_type": "",
		"notes": "",
		"tdformat": "",
		"tdline": "largest business-to-business network on the planet, we have an"
	}, {
		"__metadata": {
			"id": "https://fsc2-a73e63587.dispatcher.hana.ondemand.com/sap/opu/odata/sap/ZS_AGS_FSC2_SRV/NotesSet('0010252522')",
			"uri": "https://fsc2-a73e63587.dispatcher.hana.ondemand.com/sap/opu/odata/sap/ZS_AGS_FSC2_SRV/NotesSet('0010252522')",
			"type": "ZS_AGS_FSC2_SRV.Notes"
		},
		"id": "0010252522",
		"process_type": "ZS90",
		"notes_type": "",
		"notes": "",
		"tdformat": "",
		"tdline": "opportunity to bring greater transparency into the supply chain, so that"
	}, {
		"__metadata": {
			"id": "https://fsc2-a73e63587.dispatcher.hana.ondemand.com/sap/opu/odata/sap/ZS_AGS_FSC2_SRV/NotesSet('0010252522')",
			"uri": "https://fsc2-a73e63587.dispatcher.hana.ondemand.com/sap/opu/odata/sap/ZS_AGS_FSC2_SRV/NotesSet('0010252522')",
			"type": "ZS_AGS_FSC2_SRV.Notes"
		},
		"id": "0010252522",
		"process_type": "ZS90",
		"notes_type": "",
		"notes": "",
		"tdformat": "",
		"tdline": "buyers and suppliers can take the appropriate action to eradicate forced"
	}, {
		"__metadata": {
			"id": "https://fsc2-a73e63587.dispatcher.hana.ondemand.com/sap/opu/odata/sap/ZS_AGS_FSC2_SRV/NotesSet('0010252522')",
			"uri": "https://fsc2-a73e63587.dispatcher.hana.ondemand.com/sap/opu/odata/sap/ZS_AGS_FSC2_SRV/NotesSet('0010252522')",
			"type": "ZS_AGS_FSC2_SRV.Notes"
		},
		"id": "0010252522",
		"process_type": "ZS90",
		"notes_type": "",
		"notes": "",
		"tdformat": "",
		"tdline": "labor."
	}, {
		"__metadata": {
			"id": "https://fsc2-a73e63587.dispatcher.hana.ondemand.com/sap/opu/odata/sap/ZS_AGS_FSC2_SRV/NotesSet('0010252522')",
			"uri": "https://fsc2-a73e63587.dispatcher.hana.ondemand.com/sap/opu/odata/sap/ZS_AGS_FSC2_SRV/NotesSet('0010252522')",
			"type": "ZS_AGS_FSC2_SRV.Notes"
		},
		"id": "0010252522",
		"process_type": "ZS90",
		"notes_type": "",
		"notes": "",
		"tdformat": "*",
		"tdline": ""
	}, {
		"__metadata": {
			"id": "https://fsc2-a73e63587.dispatcher.hana.ondemand.com/sap/opu/odata/sap/ZS_AGS_FSC2_SRV/NotesSet('0010252522')",
			"uri": "https://fsc2-a73e63587.dispatcher.hana.ondemand.com/sap/opu/odata/sap/ZS_AGS_FSC2_SRV/NotesSet('0010252522')",
			"type": "ZS_AGS_FSC2_SRV.Notes"
		},
		"id": "0010252522",
		"process_type": "ZS90",
		"notes_type": "",
		"notes": "",
		"tdformat": "*",
		"tdline": "This is a challenge that’s been plaguing industries for years, but"
	}, {
		"__metadata": {
			"id": "https://fsc2-a73e63587.dispatcher.hana.ondemand.com/sap/opu/odata/sap/ZS_AGS_FSC2_SRV/NotesSet('0010252522')",
			"uri": "https://fsc2-a73e63587.dispatcher.hana.ondemand.com/sap/opu/odata/sap/ZS_AGS_FSC2_SRV/NotesSet('0010252522')",
			"type": "ZS_AGS_FSC2_SRV.Notes"
		},
		"id": "0010252522",
		"process_type": "ZS90",
		"notes_type": "",
		"notes": "",
		"tdformat": "",
		"tdline": "what’s been lacking is the appropriate levels of transparency to really"
	}, {
		"__metadata": {
			"id": "https://fsc2-a73e63587.dispatcher.hana.ondemand.com/sap/opu/odata/sap/ZS_AGS_FSC2_SRV/NotesSet('0010252522')",
			"uri": "https://fsc2-a73e63587.dispatcher.hana.ondemand.com/sap/opu/odata/sap/ZS_AGS_FSC2_SRV/NotesSet('0010252522')",
			"type": "ZS_AGS_FSC2_SRV.Notes"
		},
		"id": "0010252522",
		"process_type": "ZS90",
		"notes_type": "",
		"notes": "",
		"tdformat": "",
		"tdline": "understand where the challenges exist. So we formed a partnership with a"
	}, {
		"__metadata": {
			"id": "https://fsc2-a73e63587.dispatcher.hana.ondemand.com/sap/opu/odata/sap/ZS_AGS_FSC2_SRV/NotesSet('0010252522')",
			"uri": "https://fsc2-a73e63587.dispatcher.hana.ondemand.com/sap/opu/odata/sap/ZS_AGS_FSC2_SRV/NotesSet('0010252522')",
			"type": "ZS_AGS_FSC2_SRV.Notes"
		},
		"id": "0010252522",
		"process_type": "ZS90",
		"notes_type": "",
		"notes": "",
		"tdformat": "",
		"tdline": "company called Made In a Free World by a great person, Justin Dillon,"
	}, {
		"__metadata": {
			"id": "https://fsc2-a73e63587.dispatcher.hana.ondemand.com/sap/opu/odata/sap/ZS_AGS_FSC2_SRV/NotesSet('0010252522')",
			"uri": "https://fsc2-a73e63587.dispatcher.hana.ondemand.com/sap/opu/odata/sap/ZS_AGS_FSC2_SRV/NotesSet('0010252522')",
			"type": "ZS_AGS_FSC2_SRV.Notes"
		},
		"id": "0010252522",
		"process_type": "ZS90",
		"notes_type": "",
		"notes": "",
		"tdformat": "",
		"tdline": "and he created a heat map that showed where forced labor conditions"
	}, {
		"__metadata": {
			"id": "https://fsc2-a73e63587.dispatcher.hana.ondemand.com/sap/opu/odata/sap/ZS_AGS_FSC2_SRV/NotesSet('0010252522')",
			"uri": "https://fsc2-a73e63587.dispatcher.hana.ondemand.com/sap/opu/odata/sap/ZS_AGS_FSC2_SRV/NotesSet('0010252522')",
			"type": "ZS_AGS_FSC2_SRV.Notes"
		},
		"id": "0010252522",
		"process_type": "ZS90",
		"notes_type": "",
		"notes": "",
		"tdformat": "",
		"tdline": "exist. With the ability to pair that heat map with transactional data"
	}, {
		"__metadata": {
			"id": "https://fsc2-a73e63587.dispatcher.hana.ondemand.com/sap/opu/odata/sap/ZS_AGS_FSC2_SRV/NotesSet('0010252522')",
			"uri": "https://fsc2-a73e63587.dispatcher.hana.ondemand.com/sap/opu/odata/sap/ZS_AGS_FSC2_SRV/NotesSet('0010252522')",
			"type": "ZS_AGS_FSC2_SRV.Notes"
		},
		"id": "0010252522",
		"process_type": "ZS90",
		"notes_type": "",
		"notes": "",
		"tdformat": "",
		"tdline": "that runs through the SAP Ariba network, we can find forced labor"
	}, {
		"__metadata": {
			"id": "https://fsc2-a73e63587.dispatcher.hana.ondemand.com/sap/opu/odata/sap/ZS_AGS_FSC2_SRV/NotesSet('0010252522')",
			"uri": "https://fsc2-a73e63587.dispatcher.hana.ondemand.com/sap/opu/odata/sap/ZS_AGS_FSC2_SRV/NotesSet('0010252522')",
			"type": "ZS_AGS_FSC2_SRV.Notes"
		},
		"id": "0010252522",
		"process_type": "ZS90",
		"notes_type": "",
		"notes": "",
		"tdformat": "",
		"tdline": "conditions in their supply chain and appeal to one of the greatest needs"
	}, {
		"__metadata": {
			"id": "https://fsc2-a73e63587.dispatcher.hana.ondemand.com/sap/opu/odata/sap/ZS_AGS_FSC2_SRV/NotesSet('0010252522')",
			"uri": "https://fsc2-a73e63587.dispatcher.hana.ondemand.com/sap/opu/odata/sap/ZS_AGS_FSC2_SRV/NotesSet('0010252522')",
			"type": "ZS_AGS_FSC2_SRV.Notes"
		},
		"id": "0010252522",
		"process_type": "ZS90",
		"notes_type": "",
		"notes": "",
		"tdformat": "",
		"tdline": "of our buyers and suppliers. This is an example of companies coming"
	}, {
		"__metadata": {
			"id": "https://fsc2-a73e63587.dispatcher.hana.ondemand.com/sap/opu/odata/sap/ZS_AGS_FSC2_SRV/NotesSet('0010252522')",
			"uri": "https://fsc2-a73e63587.dispatcher.hana.ondemand.com/sap/opu/odata/sap/ZS_AGS_FSC2_SRV/NotesSet('0010252522')",
			"type": "ZS_AGS_FSC2_SRV.Notes"
		},
		"id": "0010252522",
		"process_type": "ZS90",
		"notes_type": "",
		"notes": "",
		"tdformat": "",
		"tdline": "together and recognizing the power that SAP has in having all of this"
	}, {
		"__metadata": {
			"id": "https://fsc2-a73e63587.dispatcher.hana.ondemand.com/sap/opu/odata/sap/ZS_AGS_FSC2_SRV/NotesSet('0010252522')",
			"uri": "https://fsc2-a73e63587.dispatcher.hana.ondemand.com/sap/opu/odata/sap/ZS_AGS_FSC2_SRV/NotesSet('0010252522')",
			"type": "ZS_AGS_FSC2_SRV.Notes"
		},
		"id": "0010252522",
		"process_type": "ZS90",
		"notes_type": "",
		"notes": "",
		"tdformat": "",
		"tdline": "transactional data run across SAP’s systems."
	}, {
		"__metadata": {
			"id": "https://fsc2-a73e63587.dispatcher.hana.ondemand.com/sap/opu/odata/sap/ZS_AGS_FSC2_SRV/NotesSet('0010252522')",
			"uri": "https://fsc2-a73e63587.dispatcher.hana.ondemand.com/sap/opu/odata/sap/ZS_AGS_FSC2_SRV/NotesSet('0010252522')",
			"type": "ZS_AGS_FSC2_SRV.Notes"
		},
		"id": "0010252522",
		"process_type": "ZS90",
		"notes_type": "",
		"notes": "",
		"tdformat": "*",
		"tdline": ""
	}, {
		"__metadata": {
			"id": "https://fsc2-a73e63587.dispatcher.hana.ondemand.com/sap/opu/odata/sap/ZS_AGS_FSC2_SRV/NotesSet('0010252522')",
			"uri": "https://fsc2-a73e63587.dispatcher.hana.ondemand.com/sap/opu/odata/sap/ZS_AGS_FSC2_SRV/NotesSet('0010252522')",
			"type": "ZS_AGS_FSC2_SRV.Notes"
		},
		"id": "0010252522",
		"process_type": "ZS90",
		"notes_type": "",
		"notes": "",
		"tdformat": "*",
		"tdline": "So, while prospects are asking for us to help them buy goods and connect"
	}, {
		"__metadata": {
			"id": "https://fsc2-a73e63587.dispatcher.hana.ondemand.com/sap/opu/odata/sap/ZS_AGS_FSC2_SRV/NotesSet('0010252522')",
			"uri": "https://fsc2-a73e63587.dispatcher.hana.ondemand.com/sap/opu/odata/sap/ZS_AGS_FSC2_SRV/NotesSet('0010252522')",
			"type": "ZS_AGS_FSC2_SRV.Notes"
		},
		"id": "0010252522",
		"process_type": "ZS90",
		"notes_type": "",
		"notes": "",
		"tdformat": "",
		"tdline": "them to suppliers, what we heard even more was, “Help us solve this"
	}, {
		"__metadata": {
			"id": "https://fsc2-a73e63587.dispatcher.hana.ondemand.com/sap/opu/odata/sap/ZS_AGS_FSC2_SRV/NotesSet('0010252522')",
			"uri": "https://fsc2-a73e63587.dispatcher.hana.ondemand.com/sap/opu/odata/sap/ZS_AGS_FSC2_SRV/NotesSet('0010252522')",
			"type": "ZS_AGS_FSC2_SRV.Notes"
		},
		"id": "0010252522",
		"process_type": "ZS90",
		"notes_type": "",
		"notes": "",
		"tdformat": "",
		"tdline": "unbelievable societal challenge that we have given the power of your"
	}, {
		"__metadata": {
			"id": "https://fsc2-a73e63587.dispatcher.hana.ondemand.com/sap/opu/odata/sap/ZS_AGS_FSC2_SRV/NotesSet('0010252522')",
			"uri": "https://fsc2-a73e63587.dispatcher.hana.ondemand.com/sap/opu/odata/sap/ZS_AGS_FSC2_SRV/NotesSet('0010252522')",
			"type": "ZS_AGS_FSC2_SRV.Notes"
		},
		"id": "0010252522",
		"process_type": "ZS90",
		"notes_type": "",
		"notes": "",
		"tdformat": "",
		"tdline": "network.” This was an opportunity for voices to be heard and for SAP to"
	}, {
		"__metadata": {
			"id": "https://fsc2-a73e63587.dispatcher.hana.ondemand.com/sap/opu/odata/sap/ZS_AGS_FSC2_SRV/NotesSet('0010252522')",
			"uri": "https://fsc2-a73e63587.dispatcher.hana.ondemand.com/sap/opu/odata/sap/ZS_AGS_FSC2_SRV/NotesSet('0010252522')",
			"type": "ZS_AGS_FSC2_SRV.Notes"
		},
		"id": "0010252522",
		"process_type": "ZS90",
		"notes_type": "",
		"notes": "",
		"tdformat": "",
		"tdline": "take action. Now we have an ability to offer customers the transparency"
	}, {
		"__metadata": {
			"id": "https://fsc2-a73e63587.dispatcher.hana.ondemand.com/sap/opu/odata/sap/ZS_AGS_FSC2_SRV/NotesSet('0010252522')",
			"uri": "https://fsc2-a73e63587.dispatcher.hana.ondemand.com/sap/opu/odata/sap/ZS_AGS_FSC2_SRV/NotesSet('0010252522')",
			"type": "ZS_AGS_FSC2_SRV.Notes"
		},
		"id": "0010252522",
		"process_type": "ZS90",
		"notes_type": "",
		"notes": "",
		"tdformat": "",
		"tdline": "to solve one of modern day’s most horrific challenges in supply chains."
	}, {
		"__metadata": {
			"id": "https://fsc2-a73e63587.dispatcher.hana.ondemand.com/sap/opu/odata/sap/ZS_AGS_FSC2_SRV/NotesSet('0010252522')",
			"uri": "https://fsc2-a73e63587.dispatcher.hana.ondemand.com/sap/opu/odata/sap/ZS_AGS_FSC2_SRV/NotesSet('0010252522')",
			"type": "ZS_AGS_FSC2_SRV.Notes"
		},
		"id": "0010252522",
		"process_type": "ZS90",
		"notes_type": "",
		"notes": "",
		"tdformat": "*",
		"tdline": ""
	}, {
		"__metadata": {
			"id": "https://fsc2-a73e63587.dispatcher.hana.ondemand.com/sap/opu/odata/sap/ZS_AGS_FSC2_SRV/NotesSet('0010252522')",
			"uri": "https://fsc2-a73e63587.dispatcher.hana.ondemand.com/sap/opu/odata/sap/ZS_AGS_FSC2_SRV/NotesSet('0010252522')",
			"type": "ZS_AGS_FSC2_SRV.Notes"
		},
		"id": "0010252522",
		"process_type": "ZS90",
		"notes_type": "",
		"notes": "",
		"tdformat": "*",
		"tdline": "SIMON: Given the complexity of your global footprint and your business,"
	}, {
		"__metadata": {
			"id": "https://fsc2-a73e63587.dispatcher.hana.ondemand.com/sap/opu/odata/sap/ZS_AGS_FSC2_SRV/NotesSet('0010252522')",
			"uri": "https://fsc2-a73e63587.dispatcher.hana.ondemand.com/sap/opu/odata/sap/ZS_AGS_FSC2_SRV/NotesSet('0010252522')",
			"type": "ZS_AGS_FSC2_SRV.Notes"
		},
		"id": "0010252522",
		"process_type": "ZS90",
		"notes_type": "",
		"notes": "",
		"tdformat": "",
		"tdline": "how does SAP measure and track its impact?"
	}, {
		"__metadata": {
			"id": "https://fsc2-a73e63587.dispatcher.hana.ondemand.com/sap/opu/odata/sap/ZS_AGS_FSC2_SRV/NotesSet('0010252522')",
			"uri": "https://fsc2-a73e63587.dispatcher.hana.ondemand.com/sap/opu/odata/sap/ZS_AGS_FSC2_SRV/NotesSet('0010252522')",
			"type": "ZS_AGS_FSC2_SRV.Notes"
		},
		"id": "0010252522",
		"process_type": "ZS90",
		"notes_type": "",
		"notes": "",
		"tdformat": "*",
		"tdline": ""
	}, {
		"__metadata": {
			"id": "https://fsc2-a73e63587.dispatcher.hana.ondemand.com/sap/opu/odata/sap/ZS_AGS_FSC2_SRV/NotesSet('0010252522')",
			"uri": "https://fsc2-a73e63587.dispatcher.hana.ondemand.com/sap/opu/odata/sap/ZS_AGS_FSC2_SRV/NotesSet('0010252522')",
			"type": "ZS_AGS_FSC2_SRV.Notes"
		},
		"id": "0010252522",
		"process_type": "ZS90",
		"notes_type": "",
		"notes": "",
		"tdformat": "*",
		"tdline": "ALICIA: The United Nations 17 Sustainable Development Goals are"
	}, {
		"__metadata": {
			"id": "https://fsc2-a73e63587.dispatcher.hana.ondemand.com/sap/opu/odata/sap/ZS_AGS_FSC2_SRV/NotesSet('0010252522')",
			"uri": "https://fsc2-a73e63587.dispatcher.hana.ondemand.com/sap/opu/odata/sap/ZS_AGS_FSC2_SRV/NotesSet('0010252522')",
			"type": "ZS_AGS_FSC2_SRV.Notes"
		},
		"id": "0010252522",
		"process_type": "ZS90",
		"notes_type": "",
		"notes": "",
		"tdformat": "",
		"tdline": "absolutely the framework for how we drive and track our progress as a"
	}, {
		"__metadata": {
			"id": "https://fsc2-a73e63587.dispatcher.hana.ondemand.com/sap/opu/odata/sap/ZS_AGS_FSC2_SRV/NotesSet('0010252522')",
			"uri": "https://fsc2-a73e63587.dispatcher.hana.ondemand.com/sap/opu/odata/sap/ZS_AGS_FSC2_SRV/NotesSet('0010252522')",
			"type": "ZS_AGS_FSC2_SRV.Notes"
		},
		"id": "0010252522",
		"process_type": "ZS90",
		"notes_type": "",
		"notes": "",
		"tdformat": "",
		"tdline": "company. Not only are there the technology initiatives that we help"
	}, {
		"__metadata": {
			"id": "https://fsc2-a73e63587.dispatcher.hana.ondemand.com/sap/opu/odata/sap/ZS_AGS_FSC2_SRV/NotesSet('0010252522')",
			"uri": "https://fsc2-a73e63587.dispatcher.hana.ondemand.com/sap/opu/odata/sap/ZS_AGS_FSC2_SRV/NotesSet('0010252522')",
			"type": "ZS_AGS_FSC2_SRV.Notes"
		},
		"id": "0010252522",
		"process_type": "ZS90",
		"notes_type": "",
		"notes": "",
		"tdformat": "",
		"tdline": "support, one of which I just mentioned with SAP Ariba, which would be"
	}, {
		"__metadata": {
			"id": "https://fsc2-a73e63587.dispatcher.hana.ondemand.com/sap/opu/odata/sap/ZS_AGS_FSC2_SRV/NotesSet('0010252522')",
			"uri": "https://fsc2-a73e63587.dispatcher.hana.ondemand.com/sap/opu/odata/sap/ZS_AGS_FSC2_SRV/NotesSet('0010252522')",
			"type": "ZS_AGS_FSC2_SRV.Notes"
		},
		"id": "0010252522",
		"process_type": "ZS90",
		"notes_type": "",
		"notes": "",
		"tdformat": "",
		"tdline": "paired with Goal Number 10 (Reduced Inequalities) or Number 8 (Decent"
	}, {
		"__metadata": {
			"id": "https://fsc2-a73e63587.dispatcher.hana.ondemand.com/sap/opu/odata/sap/ZS_AGS_FSC2_SRV/NotesSet('0010252522')",
			"uri": "https://fsc2-a73e63587.dispatcher.hana.ondemand.com/sap/opu/odata/sap/ZS_AGS_FSC2_SRV/NotesSet('0010252522')",
			"type": "ZS_AGS_FSC2_SRV.Notes"
		},
		"id": "0010252522",
		"process_type": "ZS90",
		"notes_type": "",
		"notes": "",
		"tdformat": "",
		"tdline": "Work). But there’s also a tremendous amount of additional programs that"
	}, {
		"__metadata": {
			"id": "https://fsc2-a73e63587.dispatcher.hana.ondemand.com/sap/opu/odata/sap/ZS_AGS_FSC2_SRV/NotesSet('0010252522')",
			"uri": "https://fsc2-a73e63587.dispatcher.hana.ondemand.com/sap/opu/odata/sap/ZS_AGS_FSC2_SRV/NotesSet('0010252522')",
			"type": "ZS_AGS_FSC2_SRV.Notes"
		},
		"id": "0010252522",
		"process_type": "ZS90",
		"notes_type": "",
		"notes": "",
		"tdformat": "",
		"tdline": "we have created within SAP that map directly to a UN goal. It helps to"
	}, {
		"__metadata": {
			"id": "https://fsc2-a73e63587.dispatcher.hana.ondemand.com/sap/opu/odata/sap/ZS_AGS_FSC2_SRV/NotesSet('0010252522')",
			"uri": "https://fsc2-a73e63587.dispatcher.hana.ondemand.com/sap/opu/odata/sap/ZS_AGS_FSC2_SRV/NotesSet('0010252522')",
			"type": "ZS_AGS_FSC2_SRV.Notes"
		},
		"id": "0010252522",
		"process_type": "ZS90",
		"notes_type": "",
		"notes": "",
		"tdformat": "",
		"tdline": "create this notion of driving impact at scale based on collaboration."
	}, {
		"__metadata": {
			"id": "https://fsc2-a73e63587.dispatcher.hana.ondemand.com/sap/opu/odata/sap/ZS_AGS_FSC2_SRV/NotesSet('0010252522')",
			"uri": "https://fsc2-a73e63587.dispatcher.hana.ondemand.com/sap/opu/odata/sap/ZS_AGS_FSC2_SRV/NotesSet('0010252522')",
			"type": "ZS_AGS_FSC2_SRV.Notes"
		},
		"id": "0010252522",
		"process_type": "ZS90",
		"notes_type": "",
		"notes": "",
		"tdformat": "*",
		"tdline": ""
	}, {
		"__metadata": {
			"id": "https://fsc2-a73e63587.dispatcher.hana.ondemand.com/sap/opu/odata/sap/ZS_AGS_FSC2_SRV/NotesSet('0010252522')",
			"uri": "https://fsc2-a73e63587.dispatcher.hana.ondemand.com/sap/opu/odata/sap/ZS_AGS_FSC2_SRV/NotesSet('0010252522')",
			"type": "ZS_AGS_FSC2_SRV.Notes"
		},
		"id": "0010252522",
		"process_type": "ZS90",
		"notes_type": "",
		"notes": "",
		"tdformat": "*",
		"tdline": "Having a framework like the 17 SDGs by the UN and getting other"
	}, {
		"__metadata": {
			"id": "https://fsc2-a73e63587.dispatcher.hana.ondemand.com/sap/opu/odata/sap/ZS_AGS_FSC2_SRV/NotesSet('0010252522')",
			"uri": "https://fsc2-a73e63587.dispatcher.hana.ondemand.com/sap/opu/odata/sap/ZS_AGS_FSC2_SRV/NotesSet('0010252522')",
			"type": "ZS_AGS_FSC2_SRV.Notes"
		},
		"id": "0010252522",
		"process_type": "ZS90",
		"notes_type": "",
		"notes": "",
		"tdformat": "",
		"tdline": "companies on board to build their purpose-driven programs means you have"
	}, {
		"__metadata": {
			"id": "https://fsc2-a73e63587.dispatcher.hana.ondemand.com/sap/opu/odata/sap/ZS_AGS_FSC2_SRV/NotesSet('0010252522')",
			"uri": "https://fsc2-a73e63587.dispatcher.hana.ondemand.com/sap/opu/odata/sap/ZS_AGS_FSC2_SRV/NotesSet('0010252522')",
			"type": "ZS_AGS_FSC2_SRV.Notes"
		},
		"id": "0010252522",
		"process_type": "ZS90",
		"notes_type": "",
		"notes": "",
		"tdformat": "",
		"tdline": "more companies and more individuals going after the same goals. The more"
	}, {
		"__metadata": {
			"id": "https://fsc2-a73e63587.dispatcher.hana.ondemand.com/sap/opu/odata/sap/ZS_AGS_FSC2_SRV/NotesSet('0010252522')",
			"uri": "https://fsc2-a73e63587.dispatcher.hana.ondemand.com/sap/opu/odata/sap/ZS_AGS_FSC2_SRV/NotesSet('0010252522')",
			"type": "ZS_AGS_FSC2_SRV.Notes"
		},
		"id": "0010252522",
		"process_type": "ZS90",
		"notes_type": "",
		"notes": "",
		"tdformat": "",
		"tdline": "we can come together as a collective force, the greater our chances are"
	}, {
		"__metadata": {
			"id": "https://fsc2-a73e63587.dispatcher.hana.ondemand.com/sap/opu/odata/sap/ZS_AGS_FSC2_SRV/NotesSet('0010252522')",
			"uri": "https://fsc2-a73e63587.dispatcher.hana.ondemand.com/sap/opu/odata/sap/ZS_AGS_FSC2_SRV/NotesSet('0010252522')",
			"type": "ZS_AGS_FSC2_SRV.Notes"
		},
		"id": "0010252522",
		"process_type": "ZS90",
		"notes_type": "",
		"notes": "",
		"tdformat": "",
		"tdline": "in actually impacting what the goals are. We have an organization within"
	}, {
		"__metadata": {
			"id": "https://fsc2-a73e63587.dispatcher.hana.ondemand.com/sap/opu/odata/sap/ZS_AGS_FSC2_SRV/NotesSet('0010252522')",
			"uri": "https://fsc2-a73e63587.dispatcher.hana.ondemand.com/sap/opu/odata/sap/ZS_AGS_FSC2_SRV/NotesSet('0010252522')",
			"type": "ZS_AGS_FSC2_SRV.Notes"
		},
		"id": "0010252522",
		"process_type": "ZS90",
		"notes_type": "",
		"notes": "",
		"tdformat": "",
		"tdline": "SAP called SAP Next-Gen and their primary focus is our relationship with"
	}, {
		"__metadata": {
			"id": "https://fsc2-a73e63587.dispatcher.hana.ondemand.com/sap/opu/odata/sap/ZS_AGS_FSC2_SRV/NotesSet('0010252522')",
			"uri": "https://fsc2-a73e63587.dispatcher.hana.ondemand.com/sap/opu/odata/sap/ZS_AGS_FSC2_SRV/NotesSet('0010252522')",
			"type": "ZS_AGS_FSC2_SRV.Notes"
		},
		"id": "0010252522",
		"process_type": "ZS90",
		"notes_type": "",
		"notes": "",
		"tdformat": "",
		"tdline": "the UN, building programs and architecting the support not only within"
	}, {
		"__metadata": {
			"id": "https://fsc2-a73e63587.dispatcher.hana.ondemand.com/sap/opu/odata/sap/ZS_AGS_FSC2_SRV/NotesSet('0010252522')",
			"uri": "https://fsc2-a73e63587.dispatcher.hana.ondemand.com/sap/opu/odata/sap/ZS_AGS_FSC2_SRV/NotesSet('0010252522')",
			"type": "ZS_AGS_FSC2_SRV.Notes"
		},
		"id": "0010252522",
		"process_type": "ZS90",
		"notes_type": "",
		"notes": "",
		"tdformat": "",
		"tdline": "SAP, but with our partners as well. Whether it’s the Global Compact"
	}, {
		"__metadata": {
			"id": "https://fsc2-a73e63587.dispatcher.hana.ondemand.com/sap/opu/odata/sap/ZS_AGS_FSC2_SRV/NotesSet('0010252522')",
			"uri": "https://fsc2-a73e63587.dispatcher.hana.ondemand.com/sap/opu/odata/sap/ZS_AGS_FSC2_SRV/NotesSet('0010252522')",
			"type": "ZS_AGS_FSC2_SRV.Notes"
		},
		"id": "0010252522",
		"process_type": "ZS90",
		"notes_type": "",
		"notes": "",
		"tdformat": "",
		"tdline": "Program or the UN for Women, there now are many different communities"
	}, {
		"__metadata": {
			"id": "https://fsc2-a73e63587.dispatcher.hana.ondemand.com/sap/opu/odata/sap/ZS_AGS_FSC2_SRV/NotesSet('0010252522')",
			"uri": "https://fsc2-a73e63587.dispatcher.hana.ondemand.com/sap/opu/odata/sap/ZS_AGS_FSC2_SRV/NotesSet('0010252522')",
			"type": "ZS_AGS_FSC2_SRV.Notes"
		},
		"id": "0010252522",
		"process_type": "ZS90",
		"notes_type": "",
		"notes": "",
		"tdformat": "",
		"tdline": "within SAP that were created in support of the 17 goals and we have an"
	}, {
		"__metadata": {
			"id": "https://fsc2-a73e63587.dispatcher.hana.ondemand.com/sap/opu/odata/sap/ZS_AGS_FSC2_SRV/NotesSet('0010252522')",
			"uri": "https://fsc2-a73e63587.dispatcher.hana.ondemand.com/sap/opu/odata/sap/ZS_AGS_FSC2_SRV/NotesSet('0010252522')",
			"type": "ZS_AGS_FSC2_SRV.Notes"
		},
		"id": "0010252522",
		"process_type": "ZS90",
		"notes_type": "",
		"notes": "",
		"tdformat": "",
		"tdline": "entire team focused on delivering results against them every single day."
	}, {
		"__metadata": {
			"id": "https://fsc2-a73e63587.dispatcher.hana.ondemand.com/sap/opu/odata/sap/ZS_AGS_FSC2_SRV/NotesSet('0010252522')",
			"uri": "https://fsc2-a73e63587.dispatcher.hana.ondemand.com/sap/opu/odata/sap/ZS_AGS_FSC2_SRV/NotesSet('0010252522')",
			"type": "ZS_AGS_FSC2_SRV.Notes"
		},
		"id": "0010252522",
		"process_type": "ZS90",
		"notes_type": "",
		"notes": "",
		"tdformat": "*",
		"tdline": ""
	}, {
		"__metadata": {
			"id": "https://fsc2-a73e63587.dispatcher.hana.ondemand.com/sap/opu/odata/sap/ZS_AGS_FSC2_SRV/NotesSet('0010252522')",
			"uri": "https://fsc2-a73e63587.dispatcher.hana.ondemand.com/sap/opu/odata/sap/ZS_AGS_FSC2_SRV/NotesSet('0010252522')",
			"type": "ZS_AGS_FSC2_SRV.Notes"
		},
		"id": "0010252522",
		"process_type": "ZS90",
		"notes_type": "",
		"notes": "",
		"tdformat": "*",
		"tdline": "SIMON: Have you noticed any surprising collaborations or synergies"
	}, {
		"__metadata": {
			"id": "https://fsc2-a73e63587.dispatcher.hana.ondemand.com/sap/opu/odata/sap/ZS_AGS_FSC2_SRV/NotesSet('0010252522')",
			"uri": "https://fsc2-a73e63587.dispatcher.hana.ondemand.com/sap/opu/odata/sap/ZS_AGS_FSC2_SRV/NotesSet('0010252522')",
			"type": "ZS_AGS_FSC2_SRV.Notes"
		},
		"id": "0010252522",
		"process_type": "ZS90",
		"notes_type": "",
		"notes": "",
		"tdformat": "",
		"tdline": "emerged when you so deeply commit to driving change?"
	}, {
		"__metadata": {
			"id": "https://fsc2-a73e63587.dispatcher.hana.ondemand.com/sap/opu/odata/sap/ZS_AGS_FSC2_SRV/NotesSet('0010252522')",
			"uri": "https://fsc2-a73e63587.dispatcher.hana.ondemand.com/sap/opu/odata/sap/ZS_AGS_FSC2_SRV/NotesSet('0010252522')",
			"type": "ZS_AGS_FSC2_SRV.Notes"
		},
		"id": "0010252522",
		"process_type": "ZS90",
		"notes_type": "",
		"notes": "",
		"tdformat": "*",
		"tdline": ""
	}, {
		"__metadata": {
			"id": "https://fsc2-a73e63587.dispatcher.hana.ondemand.com/sap/opu/odata/sap/ZS_AGS_FSC2_SRV/NotesSet('0010252522')",
			"uri": "https://fsc2-a73e63587.dispatcher.hana.ondemand.com/sap/opu/odata/sap/ZS_AGS_FSC2_SRV/NotesSet('0010252522')",
			"type": "ZS_AGS_FSC2_SRV.Notes"
		},
		"id": "0010252522",
		"process_type": "ZS90",
		"notes_type": "",
		"notes": "",
		"tdformat": "*",
		"tdline": "ALICIA: I would call out the partnership that we have with The Female"
	}, {
		"__metadata": {
			"id": "https://fsc2-a73e63587.dispatcher.hana.ondemand.com/sap/opu/odata/sap/ZS_AGS_FSC2_SRV/NotesSet('0010252522')",
			"uri": "https://fsc2-a73e63587.dispatcher.hana.ondemand.com/sap/opu/odata/sap/ZS_AGS_FSC2_SRV/NotesSet('0010252522')",
			"type": "ZS_AGS_FSC2_SRV.Notes"
		},
		"id": "0010252522",
		"process_type": "ZS90",
		"notes_type": "",
		"notes": "",
		"tdformat": "",
		"tdline": "Quotient. This is a group that was founded by Shelley Zalis and she’s"
	}, {
		"__metadata": {
			"id": "https://fsc2-a73e63587.dispatcher.hana.ondemand.com/sap/opu/odata/sap/ZS_AGS_FSC2_SRV/NotesSet('0010252522')",
			"uri": "https://fsc2-a73e63587.dispatcher.hana.ondemand.com/sap/opu/odata/sap/ZS_AGS_FSC2_SRV/NotesSet('0010252522')",
			"type": "ZS_AGS_FSC2_SRV.Notes"
		},
		"id": "0010252522",
		"process_type": "ZS90",
		"notes_type": "",
		"notes": "",
		"tdformat": "",
		"tdline": "really working to help solve gender inequality in the workplace. She"
	}, {
		"__metadata": {
			"id": "https://fsc2-a73e63587.dispatcher.hana.ondemand.com/sap/opu/odata/sap/ZS_AGS_FSC2_SRV/NotesSet('0010252522')",
			"uri": "https://fsc2-a73e63587.dispatcher.hana.ondemand.com/sap/opu/odata/sap/ZS_AGS_FSC2_SRV/NotesSet('0010252522')",
			"type": "ZS_AGS_FSC2_SRV.Notes"
		},
		"id": "0010252522",
		"process_type": "ZS90",
		"notes_type": "",
		"notes": "",
		"tdformat": "",
		"tdline": "created a movement around gender equality, looking at how we can fix the"
	}, {
		"__metadata": {
			"id": "https://fsc2-a73e63587.dispatcher.hana.ondemand.com/sap/opu/odata/sap/ZS_AGS_FSC2_SRV/NotesSet('0010252522')",
			"uri": "https://fsc2-a73e63587.dispatcher.hana.ondemand.com/sap/opu/odata/sap/ZS_AGS_FSC2_SRV/NotesSet('0010252522')",
			"type": "ZS_AGS_FSC2_SRV.Notes"
		},
		"id": "0010252522",
		"process_type": "ZS90",
		"notes_type": "",
		"notes": "",
		"tdformat": "",
		"tdline": "problem, especially for women in more diverse communities. It’s every"
	}, {
		"__metadata": {
			"id": "https://fsc2-a73e63587.dispatcher.hana.ondemand.com/sap/opu/odata/sap/ZS_AGS_FSC2_SRV/NotesSet('0010252522')",
			"uri": "https://fsc2-a73e63587.dispatcher.hana.ondemand.com/sap/opu/odata/sap/ZS_AGS_FSC2_SRV/NotesSet('0010252522')",
			"type": "ZS_AGS_FSC2_SRV.Notes"
		},
		"id": "0010252522",
		"process_type": "ZS90",
		"notes_type": "",
		"notes": "",
		"tdformat": "",
		"tdline": "company and every sector coming together because she’s created just such"
	}, {
		"__metadata": {
			"id": "https://fsc2-a73e63587.dispatcher.hana.ondemand.com/sap/opu/odata/sap/ZS_AGS_FSC2_SRV/NotesSet('0010252522')",
			"uri": "https://fsc2-a73e63587.dispatcher.hana.ondemand.com/sap/opu/odata/sap/ZS_AGS_FSC2_SRV/NotesSet('0010252522')",
			"type": "ZS_AGS_FSC2_SRV.Notes"
		},
		"id": "0010252522",
		"process_type": "ZS90",
		"notes_type": "",
		"notes": "",
		"tdformat": "",
		"tdline": "an exciting, engaging platform. Once again, it’s all focused on how do"
	}, {
		"__metadata": {
			"id": "https://fsc2-a73e63587.dispatcher.hana.ondemand.com/sap/opu/odata/sap/ZS_AGS_FSC2_SRV/NotesSet('0010252522')",
			"uri": "https://fsc2-a73e63587.dispatcher.hana.ondemand.com/sap/opu/odata/sap/ZS_AGS_FSC2_SRV/NotesSet('0010252522')",
			"type": "ZS_AGS_FSC2_SRV.Notes"
		},
		"id": "0010252522",
		"process_type": "ZS90",
		"notes_type": "",
		"notes": "",
		"tdformat": "",
		"tdline": "we reduce inequalities, which is number 10 of the 17 UN SDG goals."
	}, {
		"__metadata": {
			"id": "https://fsc2-a73e63587.dispatcher.hana.ondemand.com/sap/opu/odata/sap/ZS_AGS_FSC2_SRV/NotesSet('0010252522')",
			"uri": "https://fsc2-a73e63587.dispatcher.hana.ondemand.com/sap/opu/odata/sap/ZS_AGS_FSC2_SRV/NotesSet('0010252522')",
			"type": "ZS_AGS_FSC2_SRV.Notes"
		},
		"id": "0010252522",
		"process_type": "ZS90",
		"notes_type": "",
		"notes": "",
		"tdformat": "",
		"tdline": "That's just one example of the amazing communities that are being set up"
	}, {
		"__metadata": {
			"id": "https://fsc2-a73e63587.dispatcher.hana.ondemand.com/sap/opu/odata/sap/ZS_AGS_FSC2_SRV/NotesSet('0010252522')",
			"uri": "https://fsc2-a73e63587.dispatcher.hana.ondemand.com/sap/opu/odata/sap/ZS_AGS_FSC2_SRV/NotesSet('0010252522')",
			"type": "ZS_AGS_FSC2_SRV.Notes"
		},
		"id": "0010252522",
		"process_type": "ZS90",
		"notes_type": "",
		"notes": "",
		"tdformat": "",
		"tdline": "to bring companies and individuals that share the same beliefs and"
	}, {
		"__metadata": {
			"id": "https://fsc2-a73e63587.dispatcher.hana.ondemand.com/sap/opu/odata/sap/ZS_AGS_FSC2_SRV/NotesSet('0010252522')",
			"uri": "https://fsc2-a73e63587.dispatcher.hana.ondemand.com/sap/opu/odata/sap/ZS_AGS_FSC2_SRV/NotesSet('0010252522')",
			"type": "ZS_AGS_FSC2_SRV.Notes"
		},
		"id": "0010252522",
		"process_type": "ZS90",
		"notes_type": "",
		"notes": "",
		"tdformat": "",
		"tdline": "values to take action and move the conversation forward."
	}, {
		"__metadata": {
			"id": "https://fsc2-a73e63587.dispatcher.hana.ondemand.com/sap/opu/odata/sap/ZS_AGS_FSC2_SRV/NotesSet('0010252522')",
			"uri": "https://fsc2-a73e63587.dispatcher.hana.ondemand.com/sap/opu/odata/sap/ZS_AGS_FSC2_SRV/NotesSet('0010252522')",
			"type": "ZS_AGS_FSC2_SRV.Notes"
		},
		"id": "0010252522",
		"process_type": "ZS90",
		"notes_type": "",
		"notes": "",
		"tdformat": "*",
		"tdline": ""
	}, {
		"__metadata": {
			"id": "https://fsc2-a73e63587.dispatcher.hana.ondemand.com/sap/opu/odata/sap/ZS_AGS_FSC2_SRV/NotesSet('0010252522')",
			"uri": "https://fsc2-a73e63587.dispatcher.hana.ondemand.com/sap/opu/odata/sap/ZS_AGS_FSC2_SRV/NotesSet('0010252522')",
			"type": "ZS_AGS_FSC2_SRV.Notes"
		},
		"id": "0010252522",
		"process_type": "ZS90",
		"notes_type": "",
		"notes": "",
		"tdformat": "*",
		"tdline": "SIMON: Is there any cautionary tale you might share with a brand"
	}, {
		"__metadata": {
			"id": "https://fsc2-a73e63587.dispatcher.hana.ondemand.com/sap/opu/odata/sap/ZS_AGS_FSC2_SRV/NotesSet('0010252522')",
			"uri": "https://fsc2-a73e63587.dispatcher.hana.ondemand.com/sap/opu/odata/sap/ZS_AGS_FSC2_SRV/NotesSet('0010252522')",
			"type": "ZS_AGS_FSC2_SRV.Notes"
		},
		"id": "0010252522",
		"process_type": "ZS90",
		"notes_type": "",
		"notes": "",
		"tdformat": "",
		"tdline": "considering being purposeful. And any piece of advice that you would"
	}, {
		"__metadata": {
			"id": "https://fsc2-a73e63587.dispatcher.hana.ondemand.com/sap/opu/odata/sap/ZS_AGS_FSC2_SRV/NotesSet('0010252522')",
			"uri": "https://fsc2-a73e63587.dispatcher.hana.ondemand.com/sap/opu/odata/sap/ZS_AGS_FSC2_SRV/NotesSet('0010252522')",
			"type": "ZS_AGS_FSC2_SRV.Notes"
		},
		"id": "0010252522",
		"process_type": "ZS90",
		"notes_type": "",
		"notes": "",
		"tdformat": "",
		"tdline": "give any brand that’s sitting on the fence?"
	}, {
		"__metadata": {
			"id": "https://fsc2-a73e63587.dispatcher.hana.ondemand.com/sap/opu/odata/sap/ZS_AGS_FSC2_SRV/NotesSet('0010252522')",
			"uri": "https://fsc2-a73e63587.dispatcher.hana.ondemand.com/sap/opu/odata/sap/ZS_AGS_FSC2_SRV/NotesSet('0010252522')",
			"type": "ZS_AGS_FSC2_SRV.Notes"
		},
		"id": "0010252522",
		"process_type": "ZS90",
		"notes_type": "",
		"notes": "",
		"tdformat": "*",
		"tdline": ""
	}, {
		"__metadata": {
			"id": "https://fsc2-a73e63587.dispatcher.hana.ondemand.com/sap/opu/odata/sap/ZS_AGS_FSC2_SRV/NotesSet('0010252522')",
			"uri": "https://fsc2-a73e63587.dispatcher.hana.ondemand.com/sap/opu/odata/sap/ZS_AGS_FSC2_SRV/NotesSet('0010252522')",
			"type": "ZS_AGS_FSC2_SRV.Notes"
		},
		"id": "0010252522",
		"process_type": "ZS90",
		"notes_type": "",
		"notes": "",
		"tdformat": "*",
		"tdline": "ALICIA: I think I can answer both questions with the same answer. Be"
	}, {
		"__metadata": {
			"id": "https://fsc2-a73e63587.dispatcher.hana.ondemand.com/sap/opu/odata/sap/ZS_AGS_FSC2_SRV/NotesSet('0010252522')",
			"uri": "https://fsc2-a73e63587.dispatcher.hana.ondemand.com/sap/opu/odata/sap/ZS_AGS_FSC2_SRV/NotesSet('0010252522')",
			"type": "ZS_AGS_FSC2_SRV.Notes"
		},
		"id": "0010252522",
		"process_type": "ZS90",
		"notes_type": "",
		"notes": "",
		"tdformat": "",
		"tdline": "authentic. Every company, no matter how big or small, how long you’ve"
	}, {
		"__metadata": {
			"id": "https://fsc2-a73e63587.dispatcher.hana.ondemand.com/sap/opu/odata/sap/ZS_AGS_FSC2_SRV/NotesSet('0010252522')",
			"uri": "https://fsc2-a73e63587.dispatcher.hana.ondemand.com/sap/opu/odata/sap/ZS_AGS_FSC2_SRV/NotesSet('0010252522')",
			"type": "ZS_AGS_FSC2_SRV.Notes"
		},
		"id": "0010252522",
		"process_type": "ZS90",
		"notes_type": "",
		"notes": "",
		"tdformat": "",
		"tdline": "been around, how many different leaders you’ve had through the history"
	}, {
		"__metadata": {
			"id": "https://fsc2-a73e63587.dispatcher.hana.ondemand.com/sap/opu/odata/sap/ZS_AGS_FSC2_SRV/NotesSet('0010252522')",
			"uri": "https://fsc2-a73e63587.dispatcher.hana.ondemand.com/sap/opu/odata/sap/ZS_AGS_FSC2_SRV/NotesSet('0010252522')",
			"type": "ZS_AGS_FSC2_SRV.Notes"
		},
		"id": "0010252522",
		"process_type": "ZS90",
		"notes_type": "",
		"notes": "",
		"tdformat": "",
		"tdline": "of the company was founded with a purpose. Whether that was to create a"
	}, {
		"__metadata": {
			"id": "https://fsc2-a73e63587.dispatcher.hana.ondemand.com/sap/opu/odata/sap/ZS_AGS_FSC2_SRV/NotesSet('0010252522')",
			"uri": "https://fsc2-a73e63587.dispatcher.hana.ondemand.com/sap/opu/odata/sap/ZS_AGS_FSC2_SRV/NotesSet('0010252522')",
			"type": "ZS_AGS_FSC2_SRV.Notes"
		},
		"id": "0010252522",
		"process_type": "ZS90",
		"notes_type": "",
		"notes": "",
		"tdformat": "",
		"tdline": "company that could change something in the world, create something that"
	}, {
		"__metadata": {
			"id": "https://fsc2-a73e63587.dispatcher.hana.ondemand.com/sap/opu/odata/sap/ZS_AGS_FSC2_SRV/NotesSet('0010252522')",
			"uri": "https://fsc2-a73e63587.dispatcher.hana.ondemand.com/sap/opu/odata/sap/ZS_AGS_FSC2_SRV/NotesSet('0010252522')",
			"type": "ZS_AGS_FSC2_SRV.Notes"
		},
		"id": "0010252522",
		"process_type": "ZS90",
		"notes_type": "",
		"notes": "",
		"tdformat": "",
		"tdline": "doesn’t exist, or to improve something that does exist. So, if you don’t"
	}, {
		"__metadata": {
			"id": "https://fsc2-a73e63587.dispatcher.hana.ondemand.com/sap/opu/odata/sap/ZS_AGS_FSC2_SRV/NotesSet('0010252522')",
			"uri": "https://fsc2-a73e63587.dispatcher.hana.ondemand.com/sap/opu/odata/sap/ZS_AGS_FSC2_SRV/NotesSet('0010252522')",
			"type": "ZS_AGS_FSC2_SRV.Notes"
		},
		"id": "0010252522",
		"process_type": "ZS90",
		"notes_type": "",
		"notes": "",
		"tdformat": "",
		"tdline": "know what that story is, go back and find it because that’s the"
	}, {
		"__metadata": {
			"id": "https://fsc2-a73e63587.dispatcher.hana.ondemand.com/sap/opu/odata/sap/ZS_AGS_FSC2_SRV/NotesSet('0010252522')",
			"uri": "https://fsc2-a73e63587.dispatcher.hana.ondemand.com/sap/opu/odata/sap/ZS_AGS_FSC2_SRV/NotesSet('0010252522')",
			"type": "ZS_AGS_FSC2_SRV.Notes"
		},
		"id": "0010252522",
		"process_type": "ZS90",
		"notes_type": "",
		"notes": "",
		"tdformat": "",
		"tdline": "authentic you."
	}, {
		"__metadata": {
			"id": "https://fsc2-a73e63587.dispatcher.hana.ondemand.com/sap/opu/odata/sap/ZS_AGS_FSC2_SRV/NotesSet('0010252522')",
			"uri": "https://fsc2-a73e63587.dispatcher.hana.ondemand.com/sap/opu/odata/sap/ZS_AGS_FSC2_SRV/NotesSet('0010252522')",
			"type": "ZS_AGS_FSC2_SRV.Notes"
		},
		"id": "0010252522",
		"process_type": "ZS90",
		"notes_type": "",
		"notes": "",
		"tdformat": "*",
		"tdline": ""
	}, {
		"__metadata": {
			"id": "https://fsc2-a73e63587.dispatcher.hana.ondemand.com/sap/opu/odata/sap/ZS_AGS_FSC2_SRV/NotesSet('0010252522')",
			"uri": "https://fsc2-a73e63587.dispatcher.hana.ondemand.com/sap/opu/odata/sap/ZS_AGS_FSC2_SRV/NotesSet('0010252522')",
			"type": "ZS_AGS_FSC2_SRV.Notes"
		},
		"id": "0010252522",
		"process_type": "ZS90",
		"notes_type": "",
		"notes": "",
		"tdformat": "*",
		"tdline": "When I took this role 13 months ago, that’s exactly how I spent my first"
	}, {
		"__metadata": {
			"id": "https://fsc2-a73e63587.dispatcher.hana.ondemand.com/sap/opu/odata/sap/ZS_AGS_FSC2_SRV/NotesSet('0010252522')",
			"uri": "https://fsc2-a73e63587.dispatcher.hana.ondemand.com/sap/opu/odata/sap/ZS_AGS_FSC2_SRV/NotesSet('0010252522')",
			"type": "ZS_AGS_FSC2_SRV.Notes"
		},
		"id": "0010252522",
		"process_type": "ZS90",
		"notes_type": "",
		"notes": "",
		"tdformat": "",
		"tdline": "two months. I went back into the archives. I tried to understand what"
	}, {
		"__metadata": {
			"id": "https://fsc2-a73e63587.dispatcher.hana.ondemand.com/sap/opu/odata/sap/ZS_AGS_FSC2_SRV/NotesSet('0010252522')",
			"uri": "https://fsc2-a73e63587.dispatcher.hana.ondemand.com/sap/opu/odata/sap/ZS_AGS_FSC2_SRV/NotesSet('0010252522')",
			"type": "ZS_AGS_FSC2_SRV.Notes"
		},
		"id": "0010252522",
		"process_type": "ZS90",
		"notes_type": "",
		"notes": "",
		"tdformat": "",
		"tdline": "the reasoning was behind five leaders from IBM setting off to create"
	}, {
		"__metadata": {
			"id": "https://fsc2-a73e63587.dispatcher.hana.ondemand.com/sap/opu/odata/sap/ZS_AGS_FSC2_SRV/NotesSet('0010252522')",
			"uri": "https://fsc2-a73e63587.dispatcher.hana.ondemand.com/sap/opu/odata/sap/ZS_AGS_FSC2_SRV/NotesSet('0010252522')",
			"type": "ZS_AGS_FSC2_SRV.Notes"
		},
		"id": "0010252522",
		"process_type": "ZS90",
		"notes_type": "",
		"notes": "",
		"tdformat": "",
		"tdline": "something they believed could change the world. I wanted to understand"
	}, {
		"__metadata": {
			"id": "https://fsc2-a73e63587.dispatcher.hana.ondemand.com/sap/opu/odata/sap/ZS_AGS_FSC2_SRV/NotesSet('0010252522')",
			"uri": "https://fsc2-a73e63587.dispatcher.hana.ondemand.com/sap/opu/odata/sap/ZS_AGS_FSC2_SRV/NotesSet('0010252522')",
			"type": "ZS_AGS_FSC2_SRV.Notes"
		},
		"id": "0010252522",
		"process_type": "ZS90",
		"notes_type": "",
		"notes": "",
		"tdformat": "",
		"tdline": "how that served as the foundation for the company we are today. You may"
	}, {
		"__metadata": {
			"id": "https://fsc2-a73e63587.dispatcher.hana.ondemand.com/sap/opu/odata/sap/ZS_AGS_FSC2_SRV/NotesSet('0010252522')",
			"uri": "https://fsc2-a73e63587.dispatcher.hana.ondemand.com/sap/opu/odata/sap/ZS_AGS_FSC2_SRV/NotesSet('0010252522')",
			"type": "ZS_AGS_FSC2_SRV.Notes"
		},
		"id": "0010252522",
		"process_type": "ZS90",
		"notes_type": "",
		"notes": "",
		"tdformat": "",
		"tdline": "have lost it for whatever reason: acquisition, merger, leadership"
	}, {
		"__metadata": {
			"id": "https://fsc2-a73e63587.dispatcher.hana.ondemand.com/sap/opu/odata/sap/ZS_AGS_FSC2_SRV/NotesSet('0010252522')",
			"uri": "https://fsc2-a73e63587.dispatcher.hana.ondemand.com/sap/opu/odata/sap/ZS_AGS_FSC2_SRV/NotesSet('0010252522')",
			"type": "ZS_AGS_FSC2_SRV.Notes"
		},
		"id": "0010252522",
		"process_type": "ZS90",
		"notes_type": "",
		"notes": "",
		"tdformat": "",
		"tdline": "changes, a value prop has evolved… but never forget where you came from."
	}, {
		"__metadata": {
			"id": "https://fsc2-a73e63587.dispatcher.hana.ondemand.com/sap/opu/odata/sap/ZS_AGS_FSC2_SRV/NotesSet('0010252522')",
			"uri": "https://fsc2-a73e63587.dispatcher.hana.ondemand.com/sap/opu/odata/sap/ZS_AGS_FSC2_SRV/NotesSet('0010252522')",
			"type": "ZS_AGS_FSC2_SRV.Notes"
		},
		"id": "0010252522",
		"process_type": "ZS90",
		"notes_type": "",
		"notes": "",
		"tdformat": "",
		"tdline": "It’s a statement that we always try to hold to ourselves individually,"
	}, {
		"__metadata": {
			"id": "https://fsc2-a73e63587.dispatcher.hana.ondemand.com/sap/opu/odata/sap/ZS_AGS_FSC2_SRV/NotesSet('0010252522')",
			"uri": "https://fsc2-a73e63587.dispatcher.hana.ondemand.com/sap/opu/odata/sap/ZS_AGS_FSC2_SRV/NotesSet('0010252522')",
			"type": "ZS_AGS_FSC2_SRV.Notes"
		},
		"id": "0010252522",
		"process_type": "ZS90",
		"notes_type": "",
		"notes": "",
		"tdformat": "",
		"tdline": "but it’s also something we should not forget as companies. Because the"
	}, {
		"__metadata": {
			"id": "https://fsc2-a73e63587.dispatcher.hana.ondemand.com/sap/opu/odata/sap/ZS_AGS_FSC2_SRV/NotesSet('0010252522')",
			"uri": "https://fsc2-a73e63587.dispatcher.hana.ondemand.com/sap/opu/odata/sap/ZS_AGS_FSC2_SRV/NotesSet('0010252522')",
			"type": "ZS_AGS_FSC2_SRV.Notes"
		},
		"id": "0010252522",
		"process_type": "ZS90",
		"notes_type": "",
		"notes": "",
		"tdformat": "",
		"tdline": "reality is, people buy authenticity today. They buy truth and they want"
	}, {
		"__metadata": {
			"id": "https://fsc2-a73e63587.dispatcher.hana.ondemand.com/sap/opu/odata/sap/ZS_AGS_FSC2_SRV/NotesSet('0010252522')",
			"uri": "https://fsc2-a73e63587.dispatcher.hana.ondemand.com/sap/opu/odata/sap/ZS_AGS_FSC2_SRV/NotesSet('0010252522')",
			"type": "ZS_AGS_FSC2_SRV.Notes"
		},
		"id": "0010252522",
		"process_type": "ZS90",
		"notes_type": "",
		"notes": "",
		"tdformat": "",
		"tdline": "to be in relationships with real people. So it’s part of the obligation"
	}, {
		"__metadata": {
			"id": "https://fsc2-a73e63587.dispatcher.hana.ondemand.com/sap/opu/odata/sap/ZS_AGS_FSC2_SRV/NotesSet('0010252522')",
			"uri": "https://fsc2-a73e63587.dispatcher.hana.ondemand.com/sap/opu/odata/sap/ZS_AGS_FSC2_SRV/NotesSet('0010252522')",
			"type": "ZS_AGS_FSC2_SRV.Notes"
		},
		"id": "0010252522",
		"process_type": "ZS90",
		"notes_type": "",
		"notes": "",
		"tdformat": "",
		"tdline": "we have as business leaders to be those stewards of the purpose of our"
	}, {
		"__metadata": {
			"id": "https://fsc2-a73e63587.dispatcher.hana.ondemand.com/sap/opu/odata/sap/ZS_AGS_FSC2_SRV/NotesSet('0010252522')",
			"uri": "https://fsc2-a73e63587.dispatcher.hana.ondemand.com/sap/opu/odata/sap/ZS_AGS_FSC2_SRV/NotesSet('0010252522')",
			"type": "ZS_AGS_FSC2_SRV.Notes"
		},
		"id": "0010252522",
		"process_type": "ZS90",
		"notes_type": "",
		"notes": "",
		"tdformat": "",
		"tdline": "brands."
	}, {
		"__metadata": {
			"id": "https://fsc2-a73e63587.dispatcher.hana.ondemand.com/sap/opu/odata/sap/ZS_AGS_FSC2_SRV/NotesSet('0010252522')",
			"uri": "https://fsc2-a73e63587.dispatcher.hana.ondemand.com/sap/opu/odata/sap/ZS_AGS_FSC2_SRV/NotesSet('0010252522')",
			"type": "ZS_AGS_FSC2_SRV.Notes"
		},
		"id": "0010252522",
		"process_type": "ZS90",
		"notes_type": "",
		"notes": "",
		"tdformat": "*",
		"tdline": "____________________"
	}, {
		"__metadata": {
			"id": "https://fsc2-a73e63587.dispatcher.hana.ondemand.com/sap/opu/odata/sap/ZS_AGS_FSC2_SRV/NotesSet('0010252522')",
			"uri": "https://fsc2-a73e63587.dispatcher.hana.ondemand.com/sap/opu/odata/sap/ZS_AGS_FSC2_SRV/NotesSet('0010252522')",
			"type": "ZS_AGS_FSC2_SRV.Notes"
		},
		"id": "0010252522",
		"process_type": "ZS90",
		"notes_type": "",
		"notes": "",
		"tdformat": "*",
		"tdline": "Update to CIM"
	}, {
		"__metadata": {
			"id": "https://fsc2-a73e63587.dispatcher.hana.ondemand.com/sap/opu/odata/sap/ZS_AGS_FSC2_SRV/NotesSet('0010252522')",
			"uri": "https://fsc2-a73e63587.dispatcher.hana.ondemand.com/sap/opu/odata/sap/ZS_AGS_FSC2_SRV/NotesSet('0010252522')",
			"type": "ZS_AGS_FSC2_SRV.Notes"
		},
		"id": "0010252522",
		"process_type": "ZS90",
		"notes_type": "",
		"notes": "",
		"tdformat": "*",
		"tdline": "16.01.2019          02:57:42            I309444"
	}, {
		"__metadata": {
			"id": "https://fsc2-a73e63587.dispatcher.hana.ondemand.com/sap/opu/odata/sap/ZS_AGS_FSC2_SRV/NotesSet('0010252522')",
			"uri": "https://fsc2-a73e63587.dispatcher.hana.ondemand.com/sap/opu/odata/sap/ZS_AGS_FSC2_SRV/NotesSet('0010252522')",
			"type": "ZS_AGS_FSC2_SRV.Notes"
		},
		"id": "0010252522",
		"process_type": "ZS90",
		"notes_type": "",
		"notes": "",
		"tdformat": "*",
		"tdline": "Claire Wen"
	}, {
		"__metadata": {
			"id": "https://fsc2-a73e63587.dispatcher.hana.ondemand.com/sap/opu/odata/sap/ZS_AGS_FSC2_SRV/NotesSet('0010252522')",
			"uri": "https://fsc2-a73e63587.dispatcher.hana.ondemand.com/sap/opu/odata/sap/ZS_AGS_FSC2_SRV/NotesSet('0010252522')",
			"type": "ZS_AGS_FSC2_SRV.Notes"
		},
		"id": "0010252522",
		"process_type": "ZS90",
		"notes_type": "",
		"notes": "",
		"tdformat": "*",
		"tdline": ""
	}, {
		"__metadata": {
			"id": "https://fsc2-a73e63587.dispatcher.hana.ondemand.com/sap/opu/odata/sap/ZS_AGS_FSC2_SRV/NotesSet('0010252522')",
			"uri": "https://fsc2-a73e63587.dispatcher.hana.ondemand.com/sap/opu/odata/sap/ZS_AGS_FSC2_SRV/NotesSet('0010252522')",
			"type": "ZS_AGS_FSC2_SRV.Notes"
		},
		"id": "0010252522",
		"process_type": "ZS90",
		"notes_type": "",
		"notes": "",
		"tdformat": "*",
		"tdline": "ga"
	}, {
		"__metadata": {
			"id": "https://fsc2-a73e63587.dispatcher.hana.ondemand.com/sap/opu/odata/sap/ZS_AGS_FSC2_SRV/NotesSet('0010252522')",
			"uri": "https://fsc2-a73e63587.dispatcher.hana.ondemand.com/sap/opu/odata/sap/ZS_AGS_FSC2_SRV/NotesSet('0010252522')",
			"type": "ZS_AGS_FSC2_SRV.Notes"
		},
		"id": "0010252522",
		"process_type": "ZS90",
		"notes_type": "",
		"notes": "",
		"tdformat": "*",
		"tdline": "____________________"
	}, {
		"__metadata": {
			"id": "https://fsc2-a73e63587.dispatcher.hana.ondemand.com/sap/opu/odata/sap/ZS_AGS_FSC2_SRV/NotesSet('0010252522')",
			"uri": "https://fsc2-a73e63587.dispatcher.hana.ondemand.com/sap/opu/odata/sap/ZS_AGS_FSC2_SRV/NotesSet('0010252522')",
			"type": "ZS_AGS_FSC2_SRV.Notes"
		},
		"id": "0010252522",
		"process_type": "ZS90",
		"notes_type": "",
		"notes": "",
		"tdformat": "*",
		"tdline": "Business Impact."
	}, {
		"__metadata": {
			"id": "https://fsc2-a73e63587.dispatcher.hana.ondemand.com/sap/opu/odata/sap/ZS_AGS_FSC2_SRV/NotesSet('0010252522')",
			"uri": "https://fsc2-a73e63587.dispatcher.hana.ondemand.com/sap/opu/odata/sap/ZS_AGS_FSC2_SRV/NotesSet('0010252522')",
			"type": "ZS_AGS_FSC2_SRV.Notes"
		},
		"id": "0010252522",
		"process_type": "ZS90",
		"notes_type": "",
		"notes": "",
		"tdformat": "*",
		"tdline": "15.01.2019          08:59:44            I309444"
	}, {
		"__metadata": {
			"id": "https://fsc2-a73e63587.dispatcher.hana.ondemand.com/sap/opu/odata/sap/ZS_AGS_FSC2_SRV/NotesSet('0010252522')",
			"uri": "https://fsc2-a73e63587.dispatcher.hana.ondemand.com/sap/opu/odata/sap/ZS_AGS_FSC2_SRV/NotesSet('0010252522')",
			"type": "ZS_AGS_FSC2_SRV.Notes"
		},
		"id": "0010252522",
		"process_type": "ZS90",
		"notes_type": "",
		"notes": "",
		"tdformat": "*",
		"tdline": "Claire Wen"
	}, {
		"__metadata": {
			"id": "https://fsc2-a73e63587.dispatcher.hana.ondemand.com/sap/opu/odata/sap/ZS_AGS_FSC2_SRV/NotesSet('0010252522')",
			"uri": "https://fsc2-a73e63587.dispatcher.hana.ondemand.com/sap/opu/odata/sap/ZS_AGS_FSC2_SRV/NotesSet('0010252522')",
			"type": "ZS_AGS_FSC2_SRV.Notes"
		},
		"id": "0010252522",
		"process_type": "ZS90",
		"notes_type": "",
		"notes": "",
		"tdformat": "*",
		"tdline": ""
	}, {
		"__metadata": {
			"id": "https://fsc2-a73e63587.dispatcher.hana.ondemand.com/sap/opu/odata/sap/ZS_AGS_FSC2_SRV/NotesSet('0010252522')",
			"uri": "https://fsc2-a73e63587.dispatcher.hana.ondemand.com/sap/opu/odata/sap/ZS_AGS_FSC2_SRV/NotesSet('0010252522')",
			"type": "ZS_AGS_FSC2_SRV.Notes"
		},
		"id": "0010252522",
		"process_type": "ZS90",
		"notes_type": "",
		"notes": "",
		"tdformat": "*",
		"tdline": "fsadfsa"
	}, {
		"__metadata": {
			"id": "https://fsc2-a73e63587.dispatcher.hana.ondemand.com/sap/opu/odata/sap/ZS_AGS_FSC2_SRV/NotesSet('0010252522')",
			"uri": "https://fsc2-a73e63587.dispatcher.hana.ondemand.com/sap/opu/odata/sap/ZS_AGS_FSC2_SRV/NotesSet('0010252522')",
			"type": "ZS_AGS_FSC2_SRV.Notes"
		},
		"id": "0010252522",
		"process_type": "ZS90",
		"notes_type": "",
		"notes": "",
		"tdformat": "*",
		"tdline": "____________________"
	}, {
		"__metadata": {
			"id": "https://fsc2-a73e63587.dispatcher.hana.ondemand.com/sap/opu/odata/sap/ZS_AGS_FSC2_SRV/NotesSet('0010252522')",
			"uri": "https://fsc2-a73e63587.dispatcher.hana.ondemand.com/sap/opu/odata/sap/ZS_AGS_FSC2_SRV/NotesSet('0010252522')",
			"type": "ZS_AGS_FSC2_SRV.Notes"
		},
		"id": "0010252522",
		"process_type": "ZS90",
		"notes_type": "",
		"notes": "",
		"tdformat": "*",
		"tdline": "Update to CIM"
	}, {
		"__metadata": {
			"id": "https://fsc2-a73e63587.dispatcher.hana.ondemand.com/sap/opu/odata/sap/ZS_AGS_FSC2_SRV/NotesSet('0010252522')",
			"uri": "https://fsc2-a73e63587.dispatcher.hana.ondemand.com/sap/opu/odata/sap/ZS_AGS_FSC2_SRV/NotesSet('0010252522')",
			"type": "ZS_AGS_FSC2_SRV.Notes"
		},
		"id": "0010252522",
		"process_type": "ZS90",
		"notes_type": "",
		"notes": "",
		"tdformat": "*",
		"tdline": "15.01.2019          08:59:03            I309444"
	}, {
		"__metadata": {
			"id": "https://fsc2-a73e63587.dispatcher.hana.ondemand.com/sap/opu/odata/sap/ZS_AGS_FSC2_SRV/NotesSet('0010252522')",
			"uri": "https://fsc2-a73e63587.dispatcher.hana.ondemand.com/sap/opu/odata/sap/ZS_AGS_FSC2_SRV/NotesSet('0010252522')",
			"type": "ZS_AGS_FSC2_SRV.Notes"
		},
		"id": "0010252522",
		"process_type": "ZS90",
		"notes_type": "",
		"notes": "",
		"tdformat": "*",
		"tdline": "Claire Wen"
	}, {
		"__metadata": {
			"id": "https://fsc2-a73e63587.dispatcher.hana.ondemand.com/sap/opu/odata/sap/ZS_AGS_FSC2_SRV/NotesSet('0010252522')",
			"uri": "https://fsc2-a73e63587.dispatcher.hana.ondemand.com/sap/opu/odata/sap/ZS_AGS_FSC2_SRV/NotesSet('0010252522')",
			"type": "ZS_AGS_FSC2_SRV.Notes"
		},
		"id": "0010252522",
		"process_type": "ZS90",
		"notes_type": "",
		"notes": "",
		"tdformat": "*",
		"tdline": ""
	}, {
		"__metadata": {
			"id": "https://fsc2-a73e63587.dispatcher.hana.ondemand.com/sap/opu/odata/sap/ZS_AGS_FSC2_SRV/NotesSet('0010252522')",
			"uri": "https://fsc2-a73e63587.dispatcher.hana.ondemand.com/sap/opu/odata/sap/ZS_AGS_FSC2_SRV/NotesSet('0010252522')",
			"type": "ZS_AGS_FSC2_SRV.Notes"
		},
		"id": "0010252522",
		"process_type": "ZS90",
		"notes_type": "",
		"notes": "",
		"tdformat": "*",
		"tdline": "dsfafdasfafasdf"
	}, {
		"__metadata": {
			"id": "https://fsc2-a73e63587.dispatcher.hana.ondemand.com/sap/opu/odata/sap/ZS_AGS_FSC2_SRV/NotesSet('0010252522')",
			"uri": "https://fsc2-a73e63587.dispatcher.hana.ondemand.com/sap/opu/odata/sap/ZS_AGS_FSC2_SRV/NotesSet('0010252522')",
			"type": "ZS_AGS_FSC2_SRV.Notes"
		},
		"id": "0010252522",
		"process_type": "ZS90",
		"notes_type": "",
		"notes": "",
		"tdformat": "*",
		"tdline": "____________________"
	}, {
		"__metadata": {
			"id": "https://fsc2-a73e63587.dispatcher.hana.ondemand.com/sap/opu/odata/sap/ZS_AGS_FSC2_SRV/NotesSet('0010252522')",
			"uri": "https://fsc2-a73e63587.dispatcher.hana.ondemand.com/sap/opu/odata/sap/ZS_AGS_FSC2_SRV/NotesSet('0010252522')",
			"type": "ZS_AGS_FSC2_SRV.Notes"
		},
		"id": "0010252522",
		"process_type": "ZS90",
		"notes_type": "",
		"notes": "",
		"tdformat": "*",
		"tdline": "Business Impact."
	}, {
		"__metadata": {
			"id": "https://fsc2-a73e63587.dispatcher.hana.ondemand.com/sap/opu/odata/sap/ZS_AGS_FSC2_SRV/NotesSet('0010252522')",
			"uri": "https://fsc2-a73e63587.dispatcher.hana.ondemand.com/sap/opu/odata/sap/ZS_AGS_FSC2_SRV/NotesSet('0010252522')",
			"type": "ZS_AGS_FSC2_SRV.Notes"
		},
		"id": "0010252522",
		"process_type": "ZS90",
		"notes_type": "",
		"notes": "",
		"tdformat": "*",
		"tdline": "08.01.2019          06:40:15            I309444"
	}, {
		"__metadata": {
			"id": "https://fsc2-a73e63587.dispatcher.hana.ondemand.com/sap/opu/odata/sap/ZS_AGS_FSC2_SRV/NotesSet('0010252522')",
			"uri": "https://fsc2-a73e63587.dispatcher.hana.ondemand.com/sap/opu/odata/sap/ZS_AGS_FSC2_SRV/NotesSet('0010252522')",
			"type": "ZS_AGS_FSC2_SRV.Notes"
		},
		"id": "0010252522",
		"process_type": "ZS90",
		"notes_type": "",
		"notes": "",
		"tdformat": "*",
		"tdline": "Claire Wen"
	}, {
		"__metadata": {
			"id": "https://fsc2-a73e63587.dispatcher.hana.ondemand.com/sap/opu/odata/sap/ZS_AGS_FSC2_SRV/NotesSet('0010252522')",
			"uri": "https://fsc2-a73e63587.dispatcher.hana.ondemand.com/sap/opu/odata/sap/ZS_AGS_FSC2_SRV/NotesSet('0010252522')",
			"type": "ZS_AGS_FSC2_SRV.Notes"
		},
		"id": "0010252522",
		"process_type": "ZS90",
		"notes_type": "",
		"notes": "",
		"tdformat": "*",
		"tdline": ""
	}, {
		"__metadata": {
			"id": "https://fsc2-a73e63587.dispatcher.hana.ondemand.com/sap/opu/odata/sap/ZS_AGS_FSC2_SRV/NotesSet('0010252522')",
			"uri": "https://fsc2-a73e63587.dispatcher.hana.ondemand.com/sap/opu/odata/sap/ZS_AGS_FSC2_SRV/NotesSet('0010252522')",
			"type": "ZS_AGS_FSC2_SRV.Notes"
		},
		"id": "0010252522",
		"process_type": "ZS90",
		"notes_type": "",
		"notes": "",
		"tdformat": "*",
		"tdline": "361936/2016 Solution Provided\nODT1611:cost center is not being updated\n\nInserted business impact from selected incidents:\n----------"
	}, {
		"__metadata": {
			"id": "https://fsc2-a73e63587.dispatcher.hana.ondemand.com/sap/opu/odata/sap/ZS_AGS_FSC2_SRV/NotesSet('0010252522')",
			"uri": "https://fsc2-a73e63587.dispatcher.hana.ondemand.com/sap/opu/odata/sap/ZS_AGS_FSC2_SRV/NotesSet('0010252522')",
			"type": "ZS_AGS_FSC2_SRV.Notes"
		},
		"id": "0010252522",
		"process_type": "ZS90",
		"notes_type": "",
		"notes": "",
		"tdformat": "*",
		"tdline": "\n73678/2017\nFrom: I334974-Anna Zielinska\n[4.1 SP07] OpenDocument functionality do\n14.02.2017 11:02:09\nMr. Sebastian Söltl called us"
	}, {
		"__metadata": {
			"id": "https://fsc2-a73e63587.dispatcher.hana.ondemand.com/sap/opu/odata/sap/ZS_AGS_FSC2_SRV/NotesSet('0010252522')",
			"uri": "https://fsc2-a73e63587.dispatcher.hana.ondemand.com/sap/opu/odata/sap/ZS_AGS_FSC2_SRV/NotesSet('0010252522')",
			"type": "ZS_AGS_FSC2_SRV.Notes"
		},
		"id": "0010252522",
		"process_type": "ZS90",
		"notes_type": "",
		"notes": "",
		"tdformat": "*",
		"tdline": "and requested to report a very high priority incident. Mr. Söltl provided the business impact details. The customer is going to go l"
	}, {
		"__metadata": {
			"id": "https://fsc2-a73e63587.dispatcher.hana.ondemand.com/sap/opu/odata/sap/ZS_AGS_FSC2_SRV/NotesSet('0010252522')",
			"uri": "https://fsc2-a73e63587.dispatcher.hana.ondemand.com/sap/opu/odata/sap/ZS_AGS_FSC2_SRV/NotesSet('0010252522')",
			"type": "ZS_AGS_FSC2_SRV.Notes"
		},
		"id": "0010252522",
		"process_type": "ZS90",
		"notes_type": "",
		"notes": "",
		"tdformat": "*",
		"tdline": "ive in 4 next days. Business Impact: -it's a Go-Live project issue -when is the Go-Live date to production? February 18th -what is t"
	}, {
		"__metadata": {
			"id": "https://fsc2-a73e63587.dispatcher.hana.ondemand.com/sap/opu/odata/sap/ZS_AGS_FSC2_SRV/NotesSet('0010252522')",
			"uri": "https://fsc2-a73e63587.dispatcher.hana.ondemand.com/sap/opu/odata/sap/ZS_AGS_FSC2_SRV/NotesSet('0010252522')",
			"type": "ZS_AGS_FSC2_SRV.Notes"
		},
		"id": "0010252522",
		"process_type": "ZS90",
		"notes_type": "",
		"notes": "",
		"tdformat": "*",
		"tdline": "he Go/No-go decision date? February 15th -what is the product/module name? SAP BusinessObjects -what is the project phase? testing p"
	}, {
		"__metadata": {
			"id": "https://fsc2-a73e63587.dispatcher.hana.ondemand.com/sap/opu/odata/sap/ZS_AGS_FSC2_SRV/NotesSet('0010252522')",
			"uri": "https://fsc2-a73e63587.dispatcher.hana.ondemand.com/sap/opu/odata/sap/ZS_AGS_FSC2_SRV/NotesSet('0010252522')",
			"type": "ZS_AGS_FSC2_SRV.Notes"
		},
		"id": "0010252522",
		"process_type": "ZS90",
		"notes_type": "",
		"notes": "",
		"tdformat": "*",
		"tdline": "hase -when this phase is scheduled to be completed by? February 15th -why are you not able to go-live? The customer patches the inst"
	}, {
		"__metadata": {
			"id": "https://fsc2-a73e63587.dispatcher.hana.ondemand.com/sap/opu/odata/sap/ZS_AGS_FSC2_SRV/NotesSet('0010252522')",
			"uri": "https://fsc2-a73e63587.dispatcher.hana.ondemand.com/sap/opu/odata/sap/ZS_AGS_FSC2_SRV/NotesSet('0010252522')",
			"type": "ZS_AGS_FSC2_SRV.Notes"
		},
		"id": "0010252522",
		"process_type": "ZS90",
		"notes_type": "",
		"notes": "",
		"tdformat": "*",
		"tdline": "ance and after the upgrade the functionality (OpenDocument functionality) doesn't work properly. -how many users are in production?"
	}, {
		"__metadata": {
			"id": "https://fsc2-a73e63587.dispatcher.hana.ondemand.com/sap/opu/odata/sap/ZS_AGS_FSC2_SRV/NotesSet('0010252522')",
			"uri": "https://fsc2-a73e63587.dispatcher.hana.ondemand.com/sap/opu/odata/sap/ZS_AGS_FSC2_SRV/NotesSet('0010252522')",
			"type": "ZS_AGS_FSC2_SRV.Notes"
		},
		"id": "0010252522",
		"process_type": "ZS90",
		"notes_type": "",
		"notes": "",
		"tdformat": "*",
		"tdline": "25,000 users -are there external consultants involved in the project? no -is there a workaround? there is no workaround -is the issu"
	}, {
		"__metadata": {
			"id": "https://fsc2-a73e63587.dispatcher.hana.ondemand.com/sap/opu/odata/sap/ZS_AGS_FSC2_SRV/NotesSet('0010252522')",
			"uri": "https://fsc2-a73e63587.dispatcher.hana.ondemand.com/sap/opu/odata/sap/ZS_AGS_FSC2_SRV/NotesSet('0010252522')",
			"type": "ZS_AGS_FSC2_SRV.Notes"
		},
		"id": "0010252522",
		"process_type": "ZS90",
		"notes_type": "",
		"notes": "",
		"tdformat": "*",
		"tdline": "e a showstopper for you going live? yes -if the Go-Live date is delayed, what consequences would this have? The customer needs to fi"
	}, {
		"__metadata": {
			"id": "https://fsc2-a73e63587.dispatcher.hana.ondemand.com/sap/opu/odata/sap/ZS_AGS_FSC2_SRV/NotesSet('0010252522')",
			"uri": "https://fsc2-a73e63587.dispatcher.hana.ondemand.com/sap/opu/odata/sap/ZS_AGS_FSC2_SRV/NotesSet('0010252522')",
			"type": "ZS_AGS_FSC2_SRV.Notes"
		},
		"id": "0010252522",
		"process_type": "ZS90",
		"notes_type": "",
		"notes": "",
		"tdformat": "*",
		"tdline": "x 20 issues now at the patch level. Documents cannot be refreshes. The system begins to crash. -if there is a financial loss, can yo"
	}, {
		"__metadata": {
			"id": "https://fsc2-a73e63587.dispatcher.hana.ondemand.com/sap/opu/odata/sap/ZS_AGS_FSC2_SRV/NotesSet('0010252522')",
			"uri": "https://fsc2-a73e63587.dispatcher.hana.ondemand.com/sap/opu/odata/sap/ZS_AGS_FSC2_SRV/NotesSet('0010252522')",
			"type": "ZS_AGS_FSC2_SRV.Notes"
		},
		"id": "0010252522",
		"process_type": "ZS90",
		"notes_type": "",
		"notes": "",
		"tdformat": "*",
		"tdline": "u quantify? Mr. Söltl was not able to quantify potential financial losses -are connections to system opened and log on data provided"
	}, {
		"__metadata": {
			"id": "https://fsc2-a73e63587.dispatcher.hana.ondemand.com/sap/opu/odata/sap/ZS_AGS_FSC2_SRV/NotesSet('0010252522')",
			"uri": "https://fsc2-a73e63587.dispatcher.hana.ondemand.com/sap/opu/odata/sap/ZS_AGS_FSC2_SRV/NotesSet('0010252522')",
			"type": "ZS_AGS_FSC2_SRV.Notes"
		},
		"id": "0010252522",
		"process_type": "ZS90",
		"notes_type": "",
		"notes": "",
		"tdformat": "*",
		"tdline": " in the secure area? the connections cannot be opened -the contact person: 24/7 CP: Mr. Sebastian Söltl, +49-151-601-48640 Thank you"
	}, {
		"__metadata": {
			"id": "https://fsc2-a73e63587.dispatcher.hana.ondemand.com/sap/opu/odata/sap/ZS_AGS_FSC2_SRV/NotesSet('0010252522')",
			"uri": "https://fsc2-a73e63587.dispatcher.hana.ondemand.com/sap/opu/odata/sap/ZS_AGS_FSC2_SRV/NotesSet('0010252522')",
			"type": "ZS_AGS_FSC2_SRV.Notes"
		},
		"id": "0010252522",
		"process_type": "ZS90",
		"notes_type": "",
		"notes": "",
		"tdformat": "*",
		"tdline": ". Anna Zielinska, SAP Product Support, CIC Ireland\n"
	}, {
		"__metadata": {
			"id": "https://fsc2-a73e63587.dispatcher.hana.ondemand.com/sap/opu/odata/sap/ZS_AGS_FSC2_SRV/NotesSet('0010252522')",
			"uri": "https://fsc2-a73e63587.dispatcher.hana.ondemand.com/sap/opu/odata/sap/ZS_AGS_FSC2_SRV/NotesSet('0010252522')",
			"type": "ZS_AGS_FSC2_SRV.Notes"
		},
		"id": "0010252522",
		"process_type": "ZS90",
		"notes_type": "",
		"notes": "",
		"tdformat": "*",
		"tdline": "____________________"
	}, {
		"__metadata": {
			"id": "https://fsc2-a73e63587.dispatcher.hana.ondemand.com/sap/opu/odata/sap/ZS_AGS_FSC2_SRV/NotesSet('0010252522')",
			"uri": "https://fsc2-a73e63587.dispatcher.hana.ondemand.com/sap/opu/odata/sap/ZS_AGS_FSC2_SRV/NotesSet('0010252522')",
			"type": "ZS_AGS_FSC2_SRV.Notes"
		},
		"id": "0010252522",
		"process_type": "ZS90",
		"notes_type": "",
		"notes": "",
		"tdformat": "*",
		"tdline": "Notes"
	}, {
		"__metadata": {
			"id": "https://fsc2-a73e63587.dispatcher.hana.ondemand.com/sap/opu/odata/sap/ZS_AGS_FSC2_SRV/NotesSet('0010252522')",
			"uri": "https://fsc2-a73e63587.dispatcher.hana.ondemand.com/sap/opu/odata/sap/ZS_AGS_FSC2_SRV/NotesSet('0010252522')",
			"type": "ZS_AGS_FSC2_SRV.Notes"
		},
		"id": "0010252522",
		"process_type": "ZS90",
		"notes_type": "",
		"notes": "",
		"tdformat": "*",
		"tdline": "08.01.2019          06:40:14            I309444"
	}, {
		"__metadata": {
			"id": "https://fsc2-a73e63587.dispatcher.hana.ondemand.com/sap/opu/odata/sap/ZS_AGS_FSC2_SRV/NotesSet('0010252522')",
			"uri": "https://fsc2-a73e63587.dispatcher.hana.ondemand.com/sap/opu/odata/sap/ZS_AGS_FSC2_SRV/NotesSet('0010252522')",
			"type": "ZS_AGS_FSC2_SRV.Notes"
		},
		"id": "0010252522",
		"process_type": "ZS90",
		"notes_type": "",
		"notes": "",
		"tdformat": "*",
		"tdline": "Claire Wen"
	}, {
		"__metadata": {
			"id": "https://fsc2-a73e63587.dispatcher.hana.ondemand.com/sap/opu/odata/sap/ZS_AGS_FSC2_SRV/NotesSet('0010252522')",
			"uri": "https://fsc2-a73e63587.dispatcher.hana.ondemand.com/sap/opu/odata/sap/ZS_AGS_FSC2_SRV/NotesSet('0010252522')",
			"type": "ZS_AGS_FSC2_SRV.Notes"
		},
		"id": "0010252522",
		"process_type": "ZS90",
		"notes_type": "",
		"notes": "",
		"tdformat": "*",
		"tdline": ""
	}, {
		"__metadata": {
			"id": "https://fsc2-a73e63587.dispatcher.hana.ondemand.com/sap/opu/odata/sap/ZS_AGS_FSC2_SRV/NotesSet('0010252522')",
			"uri": "https://fsc2-a73e63587.dispatcher.hana.ondemand.com/sap/opu/odata/sap/ZS_AGS_FSC2_SRV/NotesSet('0010252522')",
			"type": "ZS_AGS_FSC2_SRV.Notes"
		},
		"id": "0010252522",
		"process_type": "ZS90",
		"notes_type": "",
		"notes": "",
		"tdformat": "*",
		"tdline": "#Raise incident priority#\n\n"
	}]
}